Workbook

Sheet Project
A1: 100 MWac Solar PV + 50 MW / 200 MWh BESS CAISO SP15 — Project Finance Model

Sheet Inputs
A1: INPUTS — All Model Assumptions · 100 MWac Solar PV + 50 MW/200 MWh BESS · CAISO SP15
B3: Category | C3: Variable Name | D3: Value | E3: Unit | F3: Source Citation | G3: Notes
B4: General Assumptions
C5: Technology | D5: Single-axis tracking PV + AC-coupled Li-ion BESS | F5: Developer assumption
C6: Location Proxy | D6: CAISO SP15 — Southern California | F6: CAISO interconnection queue
C7: COD Assumption | D7: Year 1 of model (no construction period) | F7: Simplification — see Limitations
C8: Project Life | D8: 30 years | F8: Developer assumption
B10: PV Assumptions
C11: Solar Capacity (MWac) | D11: 100 | E11: MWac | F11: Developer assumption
C12: Solar Capacity (MWdc) | D12: 120 | E12: MWdc | F12: Developer assumption
C13: P50 Capacity Factor | D13: 0.27 | E13: AC basis | F13: NREL NSRDB / SAM — SP15 | G13: P50 is the base case and represents the energy production level that has a 50% probability of being exceeded in any given year.
C14: P90 Capacity Factor | D14: 0.24 | E14: AC basis | F14: NREL NSRDB / SAM — SP15 | G14: P90 is the lender case and represents the energy production level that has a 90% probability of being exceeded in any given year. Used for minimum DSCR calculation.
C15: Degradation Rate | D15: 0.005 | E15: % | F15: NREL PV Reliability Roadmap
C16: Availability / Downtime Loss | D16: 0.015 | E16: % | F16: PVWatts | G16: 1.5% is between PVWatts default (3.0%, NREL PVWatts Version 5 Manual) and best-in-class monitored systems (0.5%). Reflects new utility-scale plant with professional O&M contract. See also NREL SAM default (5.0%) for conservative upper bound
C17: Curtailment Losses | D17: 0.04 | E17: % | F17: LBNL Utility-Scale Solar 2024 | G17: 4% net curtailment loss — reflects 2023 CAISO system average of ~3% (LBNL Utility-Scale Solar 2024, Figures 27-28) adjusted upward for project life curtailment trend and storage co-location offset. Sensitivity range: 2–12%. EIA data shows 29% year-over-year increase in CAISO curtailment in 2024."
C18: Hours per Year | D18: =365*24 | E18: Hours | F18: N/A
B21: BESS Assumptions
C22: BESS Power Rating | D22: 50 | E22: MW | F22: Developer assumption
C23: BESS Storage Capacity | D23: 200 | E23: MWh | F23: Developer assumption
C24: BESS Cycles per Day | D24: 1.3 | E24: cycles/day | F24: Simplified dispatch assumption
C25: BESS Round-Trip Efficiency (RTE) | D25: 0.85 | E25: % | F25: Standard Li-ion assumption
C26: BESS Degradation Rate | D26: 0.025 | E26: % | F26: NREL ATB 2024
C27: Days per Year | D27: 365 | E27: Days | F27: N/A
B29: Revenue Assumptions
B30: PV | C30: PPA Price (Year 1) | D30: 50 | E30: $/MWh | F30: LBNL Utility-Scale Solar 2024
C31: PPA Escalator | D31: 0.01 | E31: % | F31: Price growth assumption
C32: PPA Term | D32: 20 | E32: Years | F32: Market convention
C33: Post-PPA Revenue (Merchant Price) | D33: 35 | E33: $/MWh | F33: Merchant: conservative proxy for years 21-30
B35: BESS Energy Arbitrage | C35: Discharge Price - Year 1 | D35: 65 | E35: $/MWh | F35: SP15 evening peak proxy
C36: Discharge Price Escalator Rate | D36: 0.015 | E36: % per year | F36: Price growth assumption
C37: Grid Purchase Price (Charging Cost) | D37: 25 | E37: $/MWh | F37: SP15 off-peak proxy
C38: Grid Purchase Price Escalator | D38: 0.01 | E38: % per year | F38: Price growth assumption
C39: BESS Capacity Allocated to Arbitrage | D39: 0.7 | E39: % | F39: Developer assumption
B41: BESS Resource Adequacy | C41: BESS Accredited Capacity | D41: 45 | E41: MW | F41: 90% of 50 MW nameplate; sensitivity ±20% for accreditation risk
C42: RA Price (Year 1) | D42: 6 | E42: $/kW-month | F42: CPUC RA proceedings
C43: RA Escalator Rate | D43: 0.02 | E43: % per year | F43: IRS annual adjustment proxy — 2%
B45: BESS Ancillary Services | C45: Ancillary Services Revenue — Year 1 | D45: 75 | E45: $/kW-year | F45: CAISO market — regulation + FRP
C46: Ancillary Services Escalator Rate | D46: 0.015 | E46: % per year | F46: Price growth assumption
C47: BESS Capacity Allocated to Ancillary Services | D47: 0.3 | E47: % | F47: Developer assumption
C48: CHECK CAPACITY ALLOCATION | D48: =D39+D47 | F48: N/A
B50: Cost Assumptions
B51: Capex | C51: Solar EPC Cost | D51: 0.8 | E51: $/Wdc | F51: NREL ATB 2024 — Utility-Scale PV | G51: NREL ATB 2024 base year is 1.07/Wdc(2022), derived from Ramasamy et al. (2023) bottom-up benchmark. $0.80/Wdc reflects continued module and installation cost declines through 2024. California premium of ~10% over national average assumed for labor and permitting; without this adjustment the national benchmark would support ~$0.72–$0.75/Wdc. Sensitivity range: $0.75–$1.10/Wdc on Sensitivities tab Note: ATB capex includes grid connection costs (~$0.10/Wdc); this model separates interconnection as a standalone line item ($15M).
C52: BESS EPC Cost | D52: 230 | E52: $/kWh | F52: NREL ATB 2024 — Utility-Scale Battery Storage | G52: NREL bottom-up model (Cole and Karmakar, 2025) shows $334/kWh as the 2024 starting point for a 4-hour utility-scale system. $230/kWh reflects significant Li-ion cell cost declines through 2024 driven by global manufacturing capacity expansion, consistent with current developer procurement data. NREL's low-cost 2035 projection is $147/kWh, suggesting further decline ahead. Wide uncertainty acknowledged — sensitivity range: $200–$360/kWh on Sensitivities tab.
C53: Interconnection Cost | D53: 15 | E53: $M | F53: Developer assumption — LBNL Queued Up 2024 (wide uncertainty) | G53: No standard published benchmark. Network upgrade costs are determined by the ISO interconnection study process and can range from near zero to $50M+ for a 100 MWac project depending on location, queue position, and transmission constraints. LBNL Queued Up 2024 documents this variability across CAISO. $15M represents a moderate central estimate. This is the single most uncertain capex line item in the model — sensitivity range: $5M–$40M on Sensitivities tab.
C54: Development Costs | D54: 5 | E54: $M | F54: Developer assumption
C55: Owner's Contingency | D55: 0.05 | E55: % of hard costs | F55: Industry convention (5-10% of hard costs)
C56: Financing Costs | D56: 3 | E56: $M | F56: Developer assumption
B58: Opex | C58: Solar Fixed O&M | D58: 10 | E58: $/kWac-year | F58: NREL ATB 2024 — Utility-Scale PV | G58: NREL ATB 2024 reports $24/kWac-yr as an all-in O&M figure covering maintenance labor, insurance, land lease, asset management, site security, and vegetation management. This model decomposes those costs into separate line items. The $10/kWac covers maintenance labor and component replacement only. Summing all operating cost lines (Solar O&M + BESS O&M + Land + Insurance + Asset Management + CAISO Fees) yields approximately $29/kWac-yr, consistent with the ATB benchmark.
C59: BESS Fixed O&M | D59: 8 | E59: $/kWh-year | F59: NREL ATB 2024 — Utility-Scale Battery Storage
C60: Land Lease Rate | D60: 500 | E60: $/acre-year | F60: Developer assumption — CA market rate
C61: Land Area | D61: 600 | E61: acres | F61: Developer assumption
C62: Insurance Rate | D62: 0.0025 | E62: % of Capex/year | F62: Industry convention (0.20–0.35% of capex)
C63: Asset Management Fee | D63: 150 | E63: $K/year | F63: Developer assumption
C64: Transmission / CAISO Fees | D64: 1 | E64: $M/year | F64: Developer assumption — CAISO tariff
C65: Opex Escalator Rate | D65: 0.02 | E65: % per year | F65: IRS annual adjustment proxy — 2%
B68: Debt Assumptions
C69: Minimum DSCR Covenant | D69: 1.3 | E69: x | F69: Market convention — lender requirement
C70: Debt Interest Rate | D70: 0.07 | E70: % | F70: NREL ATB 2024 Financial Cases | G70: NREL ATB 2024 Financial Cases document a real debt rate of 4.5–5.0% for utility-scale solar. Adding the 2.5% inflation assumption used throughout the ATB gives a nominal equivalent of 7.0–7.5%. Norton Rose Fulbright Tax Equity Market Outlook 2024 confirms median project finance debt rates of approximately 7.0% for contracted utility solar as of 2023–2024. Note: ATB uses real rates for LCOE calculations; this model uses nominal rates throughout for consistency with standard project finance practice.
C71: Debt Tenor | D71: 18 | E71: Years | F71: Industry convention — solar project finance
C72: Target Debt Ratio | D72: 0.6 | E72: % | F72: Developer assumption — Goal Seek starting point
C73: Maximum Leverage | D73: 0.65 | E73: % | F73: Market convention — lender hard cap
B76: Tax Assumptions
C77: PWA Compliance | D77: YES | E77: Toggle YES/NO | F77: IRA Section 48E / 45Y — PWA requirement | G77: Toggle YES/No - drives credit rate
C78: Optimal Tax Credit Election | D78: =Tax!C54 | F78: Model-calculated — see TAX tab Block 4
C79: Tax Credit Election | D79: ITC | F79: Override toggle — defaults to model optimal | G79: TAX tab Block 4 shows PTC is the NPV-optimal election (+$5M total economic value vs. ITC). ITC is elected because PTC credits arrive annually over 10 years rather than at close, which doubles the required equity contribution from $44M to $90M and reduces Equity IRR from 9.52% to 3.69%. ITC is preferred for equity return optimization despite lower total NPV. See TAX tab Block 4 for full comparison including depreciation basis differential. This reflects the post-IRA transferability framework under Section 6418.
C80: Section 45Y PTC Rate - w/o PWA | D80: =0.006*1000 | E80: $/MWh | F80: IRA Section 45Y — base rate
C81: Section 45Y PTC Rate - w/ PWA | D81: 30 | E81: $/MWh | F81: IRA Section 45Y — 5x PWA multiplier
C82: PTC Rate Applied | D82: =IF(D77="YES",D81,D80) | E82: $/MWh | F82: Derived — see PWA Compliance toggle
C83: PTC Transfer Price | D83: 0.925 | E83: $ | F83: Norton Rose Tax Equity Outlook 2024
C84: PTC Inflation Escalator | D84: 0.02 | E84: % | F84: IRS annual adjustment proxy — 2%
C85: Section 48E ITC Rate - w/o PWA | D85: 0.06 | E85: % | F85: IRA Section 48E — base rate
C86: Section 48E ITC Rate - w/ PWA | D86: 0.3 | E86: % | F86: IRA Section 48E — 5x PWA multiplier
C87: ITC Rate Applied | D87: =IF(D77="YES",D86,D85) | E87: % | F87: Derived — see PWA Compliance toggle
C88: ITC Transfer Price | D88: 0.925 | E88: $ | F88: Norton Rose Tax Equity Outlook 2024
C89: Corporate Tax Rate | D89: 0.21 | E89: % | F89: Tax Cuts and Jobs Act 2017
C90: Net Operating Loss (NOL) Deduction Cap | D90: 0.8 | E90: % | F90: §172
C91: MACRS Schedule | D91: 5 | E91: Years | F91: IRS Publication 946 — 5-year property
C92: MACRS Year 1 | D92: 0.2 | E92: % | F92: IRS Publication 946 — half-year convention
C93: MACRS Year 2 | D93: 0.32 | E93: % | F93: IRS Publication 946 — half-year convention
C94: MACRS Year 3 | D94: 0.192 | E94: % | F94: IRS Publication 946 — half-year convention
C95: MACRS Year 4 | D95: 0.1152 | E95: % | F95: IRS Publication 946 — half-year convention
C96: MACRS Year 5 | D96: 0.1152 | E96: % | F96: IRS Publication 946 — half-year convention
C97: MACRS Year 6 | D97: =5.67%+0.09% | E97: % | F97: IRS Publication 946 — half-year convention
C98: MACRS Check | D98: =SUM(D92:D97) | E98: % | F98: N/A
B100: Discount Rate / Returns Assumptions
C101: Project Discount Rate (LCOE) | D101: 0.07 | E101: % | F101: NREL ATB 2024 Financial Cases
C102: Target Equity IRR | D102: 0.12 | E102: % | F102: Developer return threshold — industry convention

Sheet Energy
A1: ENERGY — Annual Production Schedule · Solar Loss Waterfall + BESS Dispatch · Years 1–30
A2: Year N Production | B2: 1 | C2: 2 | D2: 3 | E2: 4 | F2: 5 | G2: 6 | H2: 7 | I2: 8 | J2: 9 | K2: 10 | L2: 11 | M2: 12 | N2: 13 | O2: 14 | P2: 15 | Q2: 16 | R2: 17 | S2: 18 | T2: 19 | U2: 20 | V2: 21 | W2: 22 | X2: 23 | Y2: 24 | Z2: 25 | AA2: 26 | AB2: 27 | AC2: 28 | AD2: 29 | AE2: 30
A3: Gross Solar Production (MWh) - Pre-Degradation | B3: =Inputs!$D$11*Inputs!$D$13*Inputs!$D$18 | C3: =Inputs!$D$11*Inputs!$D$13*Inputs!$D$18 | D3: =Inputs!$D$11*Inputs!$D$13*Inputs!$D$18 | E3: =Inputs!$D$11*Inputs!$D$13*Inputs!$D$18 | F3: =Inputs!$D$11*Inputs!$D$13*Inputs!$D$18 | G3: =Inputs!$D$11*Inputs!$D$13*Inputs!$D$18 | H3: =Inputs!$D$11*Inputs!$D$13*Inputs!$D$18 | I3: =Inputs!$D$11*Inputs!$D$13*Inputs!$D$18 | ... AE3: =Inputs!$D$11*Inputs!$D$13*Inputs!$D$18
A4: PV Degradation Factor (Year N) | B4: =(1-Inputs!$D$15)^(B2-1) | C4: =(1-Inputs!$D$15)^(C2-1) | D4: =(1-Inputs!$D$15)^(D2-1) | E4: =(1-Inputs!$D$15)^(E2-1) | F4: =(1-Inputs!$D$15)^(F2-1) | G4: =(1-Inputs!$D$15)^(G2-1) | H4: =(1-Inputs!$D$15)^(H2-1) | I4: =(1-Inputs!$D$15)^(I2-1) | ... AE4: =(1-Inputs!$D$15)^(AE2-1)
A5: Gross Solar Production (MWh) - Post-Degradation | B5: =B3*B4 | C5: =C3*C4 | D5: =D3*D4 | E5: =E3*E4 | F5: =F3*F4 | G5: =G3*G4 | H5: =H3*H4 | I5: =I3*I4 | ... AE5: =AE3*AE4
A6: Availability Loss (MWh) | B6: =B5*Inputs!$D$16 | C6: =C5*Inputs!$D$16 | D6: =D5*Inputs!$D$16 | E6: =E5*Inputs!$D$16 | F6: =F5*Inputs!$D$16 | G6: =G5*Inputs!$D$16 | H6: =H5*Inputs!$D$16 | I6: =I5*Inputs!$D$16 | ... AE6: =AE5*Inputs!$D$16
A7: Production After Availability | B7: =B5-B6 | C7: =C5-C6 | D7: =D5-D6 | E7: =E5-E6 | F7: =F5-F6 | G7: =G5-G6 | H7: =H5-H6 | I7: =I5-I6 | ... AE7: =AE5-AE6
A8: Curtailment Loss (MWh) | B8: =B7*Inputs!$D$17 | C8: =C7*Inputs!$D$17 | D8: =D7*Inputs!$D$17 | E8: =E7*Inputs!$D$17 | F8: =F7*Inputs!$D$17 | G8: =G7*Inputs!$D$17 | H8: =H7*Inputs!$D$17 | I8: =I7*Inputs!$D$17 | ... AE8: =AE7*Inputs!$D$17
A9: Net Delivered Production (MWh) | B9: =B7-B8 | C9: =C7-C8 | D9: =D7-D8 | E9: =E7-E8 | F9: =F7-F8 | G9: =G7-G8 | H9: =H7-H8 | I9: =I7-I8 | ... AE9: =AE7-AE8
A11: Year N Production | B11: 1 | C11: 2 | D11: 3 | E11: 4 | F11: 5 | G11: 6 | H11: 7 | I11: 8 | J11: 9 | K11: 10 | L11: 11 | M11: 12 | N11: 13 | O11: 14 | P11: 15 | Q11: 16 | R11: 17 | S11: 18 | T11: 19 | U11: 20 | V11: 21 | W11: 22 | X11: 23 | Y11: 24 | Z11: 25 | AA11: 26 | AB11: 27 | AC11: 28 | AD11: 29 | AE11: 30
A12: BESS Gross Throughput (MWh) - Pre-Degradation | B12: =Inputs!$D$23*Inputs!$D$24*Inputs!$D$27 | C12: =Inputs!$D$23*Inputs!$D$24*Inputs!$D$27 | D12: =Inputs!$D$23*Inputs!$D$24*Inputs!$D$27 | E12: =Inputs!$D$23*Inputs!$D$24*Inputs!$D$27 | F12: =Inputs!$D$23*Inputs!$D$24*Inputs!$D$27 | G12: =Inputs!$D$23*Inputs!$D$24*Inputs!$D$27 | H12: =Inputs!$D$23*Inputs!$D$24*Inputs!$D$27 | I12: =Inputs!$D$23*Inputs!$D$24*Inputs!$D$27 | ... AE12: =Inputs!$D$23*Inputs!$D$24*Inputs!$D$27
A13: BESS Degradation Factor (Year N) | B13: =(1-Inputs!$D$26)^(Energy!B11-1) | C13: =(1-Inputs!$D$26)^(Energy!C11-1) | D13: =(1-Inputs!$D$26)^(Energy!D11-1) | E13: =(1-Inputs!$D$26)^(Energy!E11-1) | F13: =(1-Inputs!$D$26)^(Energy!F11-1) | G13: =(1-Inputs!$D$26)^(Energy!G11-1) | H13: =(1-Inputs!$D$26)^(Energy!H11-1) | I13: =(1-Inputs!$D$26)^(Energy!I11-1) | ... AE13: =(1-Inputs!$D$26)^(Energy!AE11-1)
A14: BESS Gross Throughput (MWh) - Post-Degradation | B14: =B12*B13 | C14: =C12*C13 | D14: =D12*D13 | E14: =E12*E13 | F14: =F12*F13 | G14: =G12*G13 | H14: =H12*H13 | I14: =I12*I13 | ... AE14: =AE12*AE13
A15: Curtailment Energy Available for BESS Charging (MWh) | B15: =B8 | C15: =C8 | D15: =D8 | E15: =E8 | F15: =F8 | G15: =G8 | H15: =H8 | I15: =I8 | ... AE15: =AE8
A16: Grid Charging Available (MWh) | B16: =B14-B15 | C16: =C14-C15 | D16: =D14-D15 | E16: =E14-E15 | F16: =F14-F15 | G16: =G14-G15 | H16: =H14-H15 | I16: =I14-I15 | ... AE16: =AE14-AE15
A17: BESS Gross Throughput - Constrained (MWh) | B17: =MIN(B14,SUM(B15:B16)) | C17: =MIN(C14,SUM(C15:C16)) | D17: =MIN(D14,SUM(D15:D16)) | E17: =MIN(E14,SUM(E15:E16)) | F17: =MIN(F14,SUM(F15:F16)) | G17: =MIN(G14,SUM(G15:G16)) | H17: =MIN(H14,SUM(H15:H16)) | I17: =MIN(I14,SUM(I15:I16)) | ... AE17: =MIN(AE14,SUM(AE15:AE16))
A18: Round-Trip Efficiency Loss (MWh) | B18: =B17*(1-Inputs!$D$25) | C18: =C17*(1-Inputs!$D$25) | D18: =D17*(1-Inputs!$D$25) | E18: =E17*(1-Inputs!$D$25) | F18: =F17*(1-Inputs!$D$25) | G18: =G17*(1-Inputs!$D$25) | H18: =H17*(1-Inputs!$D$25) | I18: =I17*(1-Inputs!$D$25) | ... AE18: =AE17*(1-Inputs!$D$25)
A19: BESS Net Discharge (MWh) | B19: =B17-B18 | C19: =C17-C18 | D19: =D17-D18 | E19: =E17-E18 | F19: =F17-F18 | G19: =G17-G18 | H19: =H17-H18 | I19: =I17-I18 | ... AE19: =AE17-AE18

Sheet Revenue
A1: REVENUE — Solar Energy · BESS Arbitrage · Resource Adequacy · Ancillary Services · Years 1–30
B2: Year N Production | C2: 1 | D2: 2 | E2: 3 | F2: 4 | G2: 5 | H2: 6 | I2: 7 | J2: 8 | K2: 9 | L2: 10 | M2: 11 | N2: 12 | O2: 13 | P2: 14 | Q2: 15 | R2: 16 | S2: 17 | T2: 18 | U2: 19 | V2: 20 | W2: 21 | X2: 22 | Y2: 23 | Z2: 24 | AA2: 25 | AB2: 26 | AC2: 27 | AD2: 28 | AE2: 29 | AF2: 30
A3: Solar Energy Revenue
B4: Net Delivered Solar Production (MWh) | C4: =Energy!B9 | D4: =Energy!C9 | E4: =Energy!D9 | F4: =Energy!E9 | G4: =Energy!F9 | H4: =Energy!G9 | I4: =Energy!H9 | J4: =Energy!I9 | ... AF4: =Energy!AE9
B5: PPA Price — Year 1 ($/MWh) | C5: =Inputs!$D$30 | D5: =Inputs!$D$30 | E5: =Inputs!$D$30 | F5: =Inputs!$D$30 | G5: =Inputs!$D$30 | H5: =Inputs!$D$30 | I5: =Inputs!$D$30 | J5: =Inputs!$D$30 | ... AF5: =Inputs!$D$30
B6: PPA Escalator Factor | C6: =(1+Inputs!$D$31)^(Revenue!C2-1) | D6: =(1+Inputs!$D$31)^(Revenue!D2-1) | E6: =(1+Inputs!$D$31)^(Revenue!E2-1) | F6: =(1+Inputs!$D$31)^(Revenue!F2-1) | G6: =(1+Inputs!$D$31)^(Revenue!G2-1) | H6: =(1+Inputs!$D$31)^(Revenue!H2-1) | I6: =(1+Inputs!$D$31)^(Revenue!I2-1) | J6: =(1+Inputs!$D$31)^(Revenue!J2-1) | ... AF6: =(1+Inputs!$D$31)^(Revenue!AF2-1)
B7: PPA Price — Escalated ($/MWh) | C7: =C5*C6 | D7: =D5*D6 | E7: =E5*E6 | F7: =F5*F6 | G7: =G5*G6 | H7: =H5*H6 | I7: =I5*I6 | J7: =J5*J6 | ... AF7: =AF5*AF6
B8: Merchant Price ($/MWh) | C8: =Inputs!$D$33 | D8: =Inputs!$D$33 | E8: =Inputs!$D$33 | F8: =Inputs!$D$33 | G8: =Inputs!$D$33 | H8: =Inputs!$D$33 | I8: =Inputs!$D$33 | J8: =Inputs!$D$33 | ... AF8: =Inputs!$D$33
B9: Contract Period Flag | C9: =IF(C2<=Inputs!$D$32,"PPA","Merchant") | D9: =IF(D2<=Inputs!$D$32,"PPA","Merchant") | E9: =IF(E2<=Inputs!$D$32,"PPA","Merchant") | F9: =IF(F2<=Inputs!$D$32,"PPA","Merchant") | G9: =IF(G2<=Inputs!$D$32,"PPA","Merchant") | H9: =IF(H2<=Inputs!$D$32,"PPA","Merchant") | I9: =IF(I2<=Inputs!$D$32,"PPA","Merchant") | J9: =IF(J2<=Inputs!$D$32,"PPA","Merchant") | ... AF9: =IF(AF2<=Inputs!$D$32,"PPA","Merchant")
B10: Effective Energy Price — Year N ($/MWh) | C10: =IF(Revenue!C2<=Inputs!$D$32,Revenue!C7,Revenue!C8) | D10: =IF(Revenue!D2<=Inputs!$D$32,Revenue!D7,Revenue!D8) | E10: =IF(Revenue!E2<=Inputs!$D$32,Revenue!E7,Revenue!E8) | F10: =IF(Revenue!F2<=Inputs!$D$32,Revenue!F7,Revenue!F8) | G10: =IF(Revenue!G2<=Inputs!$D$32,Revenue!G7,Revenue!G8) | H10: =IF(Revenue!H2<=Inputs!$D$32,Revenue!H7,Revenue!H8) | I10: =IF(Revenue!I2<=Inputs!$D$32,Revenue!I7,Revenue!I8) | J10: =IF(Revenue!J2<=Inputs!$D$32,Revenue!J7,Revenue!J8) | ... AF10: =IF(Revenue!AF2<=Inputs!$D$32,Revenue!AF7,Revenue!AF8)
B11: Solar Energy Revenue ($) | C11: =C10*C4 | D11: =D10*D4 | E11: =E10*E4 | F11: =F10*F4 | G11: =G10*G4 | H11: =H10*H4 | I11: =I10*I4 | J11: =J10*J4 | ... AF11: =AF10*AF4
A13: BESS Block 1 - Energy Arbitrage Revenue
B14: BESS Net Discharge (MWh) | C14: =Energy!B19 | D14: =Energy!C19 | E14: =Energy!D19 | F14: =Energy!E19 | G14: =Energy!F19 | H14: =Energy!G19 | I14: =Energy!H19 | J14: =Energy!I19 | ... AF14: =Energy!AE19
B15: BESS Capacity Allocated to Arbitrage | C15: =Inputs!$D$39 | D15: =Inputs!$D$39 | E15: =Inputs!$D$39 | F15: =Inputs!$D$39 | G15: =Inputs!$D$39 | H15: =Inputs!$D$39 | I15: =Inputs!$D$39 | J15: =Inputs!$D$39 | ... AF15: =Inputs!$D$39
B16: BESS Net Discharge - Arbitrage Share (MWh) | C16: =C14*C15 | D16: =D14*D15 | E16: =E14*E15 | F16: =F14*F15 | G16: =G14*G15 | H16: =H14*H15 | I16: =I14*I15 | J16: =J14*J15 | ... AF16: =AF14*AF15
B17: Discharge Price - Year 1 ($/MWh) | C17: =Inputs!$D$35 | D17: =Inputs!$D$35 | E17: =Inputs!$D$35 | F17: =Inputs!$D$35 | G17: =Inputs!$D$35 | H17: =Inputs!$D$35 | I17: =Inputs!$D$35 | J17: =Inputs!$D$35 | ... AF17: =Inputs!$D$35
B18: Discharge Price Escalator Factor | C18: =(1+Inputs!$D$36)^(Revenue!C2-1) | D18: =(1+Inputs!$D$36)^(Revenue!D2-1) | E18: =(1+Inputs!$D$36)^(Revenue!E2-1) | F18: =(1+Inputs!$D$36)^(Revenue!F2-1) | G18: =(1+Inputs!$D$36)^(Revenue!G2-1) | H18: =(1+Inputs!$D$36)^(Revenue!H2-1) | I18: =(1+Inputs!$D$36)^(Revenue!I2-1) | J18: =(1+Inputs!$D$36)^(Revenue!J2-1) | ... AF18: =(1+Inputs!$D$36)^(Revenue!AF2-1)
B19: Discharge Price - Year N ($/MWh) | C19: =C17*C18 | D19: =D17*D18 | E19: =E17*E18 | F19: =F17*F18 | G19: =G17*G18 | H19: =H17*H18 | I19: =I17*I18 | J19: =J17*J18 | ... AF19: =AF17*AF18
B20: Grid Purchase Price - Year 1 ($/MWh) | C20: =Inputs!$D$37 | D20: =Inputs!$D$37 | E20: =Inputs!$D$37 | F20: =Inputs!$D$37 | G20: =Inputs!$D$37 | H20: =Inputs!$D$37 | I20: =Inputs!$D$37 | J20: =Inputs!$D$37 | ... AF20: =Inputs!$D$37
B21: Grid Purchase Price Escalator Factor | C21: =(1+Inputs!$D$38)^(Revenue!C2-1) | D21: =(1+Inputs!$D$38)^(Revenue!D2-1) | E21: =(1+Inputs!$D$38)^(Revenue!E2-1) | F21: =(1+Inputs!$D$38)^(Revenue!F2-1) | G21: =(1+Inputs!$D$38)^(Revenue!G2-1) | H21: =(1+Inputs!$D$38)^(Revenue!H2-1) | I21: =(1+Inputs!$D$38)^(Revenue!I2-1) | J21: =(1+Inputs!$D$38)^(Revenue!J2-1) | ... AF21: =(1+Inputs!$D$38)^(Revenue!AF2-1)
B22: Grid Purchase Price - Year N ($/MWh) | C22: =C20*C21 | D22: =D20*D21 | E22: =E20*E21 | F22: =F20*F21 | G22: =G20*G21 | H22: =H20*H21 | I22: =I20*I21 | J22: =J20*J21 | ... AF22: =AF20*AF21
B23: RTE Adjustment Factor | C23: =1/Inputs!$D$25 | D23: =1/Inputs!$D$25 | E23: =1/Inputs!$D$25 | F23: =1/Inputs!$D$25 | G23: =1/Inputs!$D$25 | H23: =1/Inputs!$D$25 | I23: =1/Inputs!$D$25 | J23: =1/Inputs!$D$25 | ... AF23: =1/Inputs!$D$25
B24: Charging Cost per MWh Delivered - Year N ($/MWh) | C24: =C22*C23 | D24: =D22*D23 | E24: =E22*E23 | F24: =F22*F23 | G24: =G22*G23 | H24: =H22*H23 | I24: =I22*I23 | J24: =J22*J23 | ... AF24: =AF22*AF23
B25: Curtailment Share of Charging (%) | C25: =Energy!B15/Energy!B17 | D25: =Energy!C15/Energy!C17 | E25: =Energy!D15/Energy!D17 | F25: =Energy!E15/Energy!E17 | G25: =Energy!F15/Energy!F17 | H25: =Energy!G15/Energy!G17 | I25: =Energy!H15/Energy!H17 | J25: =Energy!I15/Energy!I17 | ... AF25: =Energy!AE15/Energy!AE17
B26: Grid Charging Share (%) | C26: =1-C25 | D26: =1-D25 | E26: =1-E25 | F26: =1-F25 | G26: =1-G25 | H26: =1-H25 | I26: =1-I25 | J26: =1-J25 | ... AF26: =1-AF25
B27: Blended Charging Cost ($/MWh) | C27: =C26*C24 | D27: =D26*D24 | E27: =E26*E24 | F27: =F26*F24 | G27: =G26*G24 | H27: =H26*H24 | I27: =I26*I24 | J27: =J26*J24 | ... AF27: =AF26*AF24
B28: Gross Arbitrage Spread - Year N ($/MWh) | C28: =C19-C27 | D28: =D19-D27 | E28: =E19-E27 | F28: =F19-F27 | G28: =G19-G27 | H28: =H19-H27 | I28: =I19-I27 | J28: =J19-J27 | ... AF28: =AF19-AF27
B29: BESS Energy Arbitrage Revenue ($) | C29: =C16*C28 | D29: =D16*D28 | E29: =E16*E28 | F29: =F16*F28 | G29: =G16*G28 | H29: =H16*H28 | I29: =I16*I28 | J29: =J16*J28 | ... AF29: =AF16*AF28
A31: BESS Block 2 — Resource Adequacy Revenue
B32: BESS Accredited Capacity (MW) | C32: =Inputs!$D$41 | D32: =Inputs!$D$41 | E32: =Inputs!$D$41 | F32: =Inputs!$D$41 | G32: =Inputs!$D$41 | H32: =Inputs!$D$41 | I32: =Inputs!$D$41 | J32: =Inputs!$D$41 | ... AF32: =Inputs!$D$41
B33: RA Price — Year 1 ($/kW-month) | C33: =Inputs!$D$42 | D33: =Inputs!$D$42 | E33: =Inputs!$D$42 | F33: =Inputs!$D$42 | G33: =Inputs!$D$42 | H33: =Inputs!$D$42 | I33: =Inputs!$D$42 | J33: =Inputs!$D$42 | ... AF33: =Inputs!$D$42
B34: RA Escalator Factor | C34: =(1+Inputs!$D$43)^(Revenue!C2-1) | D34: =(1+Inputs!$D$43)^(Revenue!D2-1) | E34: =(1+Inputs!$D$43)^(Revenue!E2-1) | F34: =(1+Inputs!$D$43)^(Revenue!F2-1) | G34: =(1+Inputs!$D$43)^(Revenue!G2-1) | H34: =(1+Inputs!$D$43)^(Revenue!H2-1) | I34: =(1+Inputs!$D$43)^(Revenue!I2-1) | J34: =(1+Inputs!$D$43)^(Revenue!J2-1) | ... AF34: =(1+Inputs!$D$43)^(Revenue!AF2-1)
B35: RA Price — Year N ($/kW-month) | C35: =C33*C34 | D35: =D33*D34 | E35: =E33*E34 | F35: =F33*F34 | G35: =G33*G34 | H35: =H33*H34 | I35: =I33*I34 | J35: =J33*J34 | ... AF35: =AF33*AF34
B36: BESS RA Revenue ($) | C36: =C32*C35*12*1000 | D36: =D32*D35*12*1000 | E36: =E32*E35*12*1000 | F36: =F32*F35*12*1000 | G36: =G32*G35*12*1000 | H36: =H32*H35*12*1000 | I36: =I32*I35*12*1000 | J36: =J32*J35*12*1000 | ... AF36: =AF32*AF35*12*1000
A38: BESS Block 3 — Ancillary Services Revenue
B39: BESS Power Rating - Nameplate (MW) | C39: =Inputs!$D$22 | D39: =Inputs!$D$22 | E39: =Inputs!$D$22 | F39: =Inputs!$D$22 | G39: =Inputs!$D$22 | H39: =Inputs!$D$22 | I39: =Inputs!$D$22 | J39: =Inputs!$D$22 | ... AF39: =Inputs!$D$22
B40: BESS Power Degradation Factor | C40: =(1-Inputs!$D$26)^(Revenue!C2-1) | D40: =(1-Inputs!$D$26)^(Revenue!D2-1) | E40: =(1-Inputs!$D$26)^(Revenue!E2-1) | F40: =(1-Inputs!$D$26)^(Revenue!F2-1) | G40: =(1-Inputs!$D$26)^(Revenue!G2-1) | H40: =(1-Inputs!$D$26)^(Revenue!H2-1) | I40: =(1-Inputs!$D$26)^(Revenue!I2-1) | J40: =(1-Inputs!$D$26)^(Revenue!J2-1) | ... AF40: =(1-Inputs!$D$26)^(Revenue!AF2-1)
B41: BESS Power Rating - Year N (MW) | C41: =C40*C39 | D41: =D40*D39 | E41: =E40*E39 | F41: =F40*F39 | G41: =G40*G39 | H41: =H40*H39 | I41: =I40*I39 | J41: =J40*J39 | ... AF41: =AF40*AF39
B42: Ancillary Services Capacity Allocation | C42: =Inputs!$D$47 | D42: =Inputs!$D$47 | E42: =Inputs!$D$47 | F42: =Inputs!$D$47 | G42: =Inputs!$D$47 | H42: =Inputs!$D$47 | I42: =Inputs!$D$47 | J42: =Inputs!$D$47 | ... AF42: =Inputs!$D$47
B43: BESS Capacity - Ancillary Services Share (MW) | C43: =C41*C42 | D43: =D41*D42 | E43: =E41*E42 | F43: =F41*F42 | G43: =G41*G42 | H43: =H41*H42 | I43: =I41*I42 | J43: =J41*J42 | ... AF43: =AF41*AF42
B44: Ancillary Services Revenue - Year 1 ($/kW-year) | C44: =Inputs!$D$45 | D44: =Inputs!$D$45 | E44: =Inputs!$D$45 | F44: =Inputs!$D$45 | G44: =Inputs!$D$45 | H44: =Inputs!$D$45 | I44: =Inputs!$D$45 | J44: =Inputs!$D$45 | ... AF44: =Inputs!$D$45
B45: Ancillary Services Escalator Factor | C45: =(1+Inputs!$D$46)^(Revenue!C2-1) | D45: =(1+Inputs!$D$46)^(Revenue!D2-1) | E45: =(1+Inputs!$D$46)^(Revenue!E2-1) | F45: =(1+Inputs!$D$46)^(Revenue!F2-1) | G45: =(1+Inputs!$D$46)^(Revenue!G2-1) | H45: =(1+Inputs!$D$46)^(Revenue!H2-1) | I45: =(1+Inputs!$D$46)^(Revenue!I2-1) | J45: =(1+Inputs!$D$46)^(Revenue!J2-1) | ... AF45: =(1+Inputs!$D$46)^(Revenue!AF2-1)
B46: Ancillary Services Revenue - Year N ($/kW-year) | C46: =C44*C45 | D46: =D44*D45 | E46: =E44*E45 | F46: =F44*F45 | G46: =G44*G45 | H46: =H44*H45 | I46: =I44*I45 | J46: =J44*J45 | ... AF46: =AF44*AF45
B47: BESS Ancillary Services Revenue ($) | C47: =C43*C46*1000 | D47: =D43*D46*1000 | E47: =E43*E46*1000 | F47: =F43*F46*1000 | G47: =G43*G46*1000 | H47: =H43*H46*1000 | I47: =I43*I46*1000 | J47: =J43*J46*1000 | ... AF47: =AF43*AF46*1000
B50: TOTAL REVENUE | C50: =C11+C29+C36+C47 | D50: =D11+D29+D36+D47 | E50: =E11+E29+E36+E47 | F50: =F11+F29+F36+F47 | G50: =G11+G29+G36+G47 | H50: =H11+H29+H36+H47 | I50: =I11+I29+I36+I47 | J50: =J11+J29+J36+J47 | ... AF50: =AF11+AF29+AF36+AF47

Sheet Costs
A1: COSTS — Capital Expenditure (Sources & Uses) · Annual Operating Costs · Years 1–30
A2: Capex
B3: Uses Block
B4: Solar EPC Cost ($) | C4: =(Inputs!$D$12*1000*1000)*Inputs!$D$51
B5: BESS EPC Cost ($) | C5: =(Inputs!$D$23*1000)*Inputs!$D$52
B6: Subtotal Hard Costs ($) | C6: =SUM(C4:C5)
B7: Interconnection Cost ($) | C7: =Inputs!$D$53*1000000
B8: Development Costs ($) | C8: =Inputs!$D$54*1000000
B9: Owner's Contingency ($) | C9: =C6*Inputs!$D$55
B10: Subtotal Soft Costs ($) | C10: =SUM(C7:C9)
B11: Subtotal Project Cost ($) | C11: =C6+C10
B12: Financing Costs ($) | C12: =Inputs!$D$56*1000000
B13: Total Project Cost ($) | C13: =C11+C12
B16: Year N Production | C16: 1 | D16: 2 | E16: 3 | F16: 4 | G16: 5 | H16: 6 | I16: 7 | J16: 8 | K16: 9 | L16: 10 | M16: 11 | N16: 12 | O16: 13 | P16: 14 | Q16: 15 | R16: 16 | S16: 17 | T16: 18 | U16: 19 | V16: 20 | W16: 21 | X16: 22 | Y16: 23 | Z16: 24 | AA16: 25 | AB16: 26 | AC16: 27 | AD16: 28 | AE16: 29 | AF16: 30
A17: Opex
B18: Opex Escalator Factor | C18: =(1+Inputs!$D$65)^(Costs!C16-1) | D18: =(1+Inputs!$D$65)^(Costs!D16-1) | E18: =(1+Inputs!$D$65)^(Costs!E16-1) | F18: =(1+Inputs!$D$65)^(Costs!F16-1) | G18: =(1+Inputs!$D$65)^(Costs!G16-1) | H18: =(1+Inputs!$D$65)^(Costs!H16-1) | I18: =(1+Inputs!$D$65)^(Costs!I16-1) | J18: =(1+Inputs!$D$65)^(Costs!J16-1) | ... AF18: =(1+Inputs!$D$65)^(Costs!AF16-1)
B19: Solar Fixed O&M ($) | C19: =Inputs!$D$58*Inputs!$D$11*1000*Costs!C18 | D19: =Inputs!$D$58*Inputs!$D$11*1000*Costs!D18 | E19: =Inputs!$D$58*Inputs!$D$11*1000*Costs!E18 | F19: =Inputs!$D$58*Inputs!$D$11*1000*Costs!F18 | G19: =Inputs!$D$58*Inputs!$D$11*1000*Costs!G18 | H19: =Inputs!$D$58*Inputs!$D$11*1000*Costs!H18 | I19: =Inputs!$D$58*Inputs!$D$11*1000*Costs!I18 | J19: =Inputs!$D$58*Inputs!$D$11*1000*Costs!J18 | ... AF19: =Inputs!$D$58*Inputs!$D$11*1000*Costs!AF18
B20: BESS Fixed O&M ($) | C20: =Inputs!$D$59*Inputs!$D$23*1000*Costs!C18 | D20: =Inputs!$D$59*Inputs!$D$23*1000*Costs!D18 | E20: =Inputs!$D$59*Inputs!$D$23*1000*Costs!E18 | F20: =Inputs!$D$59*Inputs!$D$23*1000*Costs!F18 | G20: =Inputs!$D$59*Inputs!$D$23*1000*Costs!G18 | H20: =Inputs!$D$59*Inputs!$D$23*1000*Costs!H18 | I20: =Inputs!$D$59*Inputs!$D$23*1000*Costs!I18 | J20: =Inputs!$D$59*Inputs!$D$23*1000*Costs!J18 | ... AF20: =Inputs!$D$59*Inputs!$D$23*1000*Costs!AF18
B21: Land Lease ($) | C21: =Inputs!$D$61*Inputs!$D$60*Costs!C18 | D21: =Inputs!$D$61*Inputs!$D$60*Costs!D18 | E21: =Inputs!$D$61*Inputs!$D$60*Costs!E18 | F21: =Inputs!$D$61*Inputs!$D$60*Costs!F18 | G21: =Inputs!$D$61*Inputs!$D$60*Costs!G18 | H21: =Inputs!$D$61*Inputs!$D$60*Costs!H18 | I21: =Inputs!$D$61*Inputs!$D$60*Costs!I18 | J21: =Inputs!$D$61*Inputs!$D$60*Costs!J18 | ... AF21: =Inputs!$D$61*Inputs!$D$60*Costs!AF18
B22: Insurance ($) | C22: =$C$13*Inputs!$D$62*Costs!C18 | D22: =$C$13*Inputs!$D$62*Costs!D18 | E22: =$C$13*Inputs!$D$62*Costs!E18 | F22: =$C$13*Inputs!$D$62*Costs!F18 | G22: =$C$13*Inputs!$D$62*Costs!G18 | H22: =$C$13*Inputs!$D$62*Costs!H18 | I22: =$C$13*Inputs!$D$62*Costs!I18 | J22: =$C$13*Inputs!$D$62*Costs!J18 | ... AF22: =$C$13*Inputs!$D$62*Costs!AF18
B23: Asset Management Fee ($) | C23: =Inputs!$D$63*1000*Costs!C18 | D23: =Inputs!$D$63*1000*Costs!D18 | E23: =Inputs!$D$63*1000*Costs!E18 | F23: =Inputs!$D$63*1000*Costs!F18 | G23: =Inputs!$D$63*1000*Costs!G18 | H23: =Inputs!$D$63*1000*Costs!H18 | I23: =Inputs!$D$63*1000*Costs!I18 | J23: =Inputs!$D$63*1000*Costs!J18 | ... AF23: =Inputs!$D$63*1000*Costs!AF18
B24: Transmission / CAISO Fees ($) | C24: =Inputs!$D$64*1000000*Costs!C18 | D24: =Inputs!$D$64*1000000*Costs!D18 | E24: =Inputs!$D$64*1000000*Costs!E18 | F24: =Inputs!$D$64*1000000*Costs!F18 | G24: =Inputs!$D$64*1000000*Costs!G18 | H24: =Inputs!$D$64*1000000*Costs!H18 | I24: =Inputs!$D$64*1000000*Costs!I18 | J24: =Inputs!$D$64*1000000*Costs!J18 | ... AF24: =Inputs!$D$64*1000000*Costs!AF18
B25: Total Opex ($) | C25: =SUM(C19:C24) | D25: =SUM(D19:D24) | E25: =SUM(E19:E24) | F25: =SUM(F19:F24) | G25: =SUM(G19:G24) | H25: =SUM(H19:H24) | I25: =SUM(I19:I24) | J25: =SUM(J19:J24) | ... AF25: =SUM(AF19:AF24)
B27: Opex % of Revenue | C27: =C25/Revenue!C50 | D27: =D25/Revenue!D50 | E27: =E25/Revenue!E50 | F27: =F25/Revenue!F50 | G27: =G25/Revenue!G50 | H27: =H25/Revenue!H50 | I27: =I25/Revenue!I50 | J27: =J25/Revenue!J50 | ... AF27: =AF25/Revenue!AF50
B28: Cumulative Opex ($) | C28: =C25 | D28: =C28+D25 | E28: =D28+E25 | F28: =E28+F25 | G28: =F28+G25 | H28: =G28+H25 | I28: =H28+I25 | J28: =I28+J25 | K28: =J28+K25 | ... AF28: =AE28+AF25

Sheet Debt
A1: DEBT — Debt Sizing · Amortization Schedule · DSCR · Goal Seek: Set Min DSCR = 1.30x by changing Initial Debt Estimate
A2: Block 1 — Debt Sizing
B3: Total Project Cost ($) | C3: =Costs!$C$13
B4: ITC Cash Proceeds ($) | C4: =IF(Inputs!$D$79="ITC",Tax!$C$10,0)
B5: Target Debt: Total Capitalization (%) | C5: =Inputs!$D$72
B6: Initial Debt Estimate ($) | C6: 99095616
B7: Minimum DSCR Covenant | C7: =Inputs!$D$69
B8: Debt Interest Rate | C8: =Inputs!$D$70
B9: Debt Tenor (years) | C9: =Inputs!$D$71
B10: Annual Debt Service — Constant ($) | C10: =ABS(PMT(C8,C9,C6))
B11: Minimum DSCR Achieved | C11: =C49
B12: Sizing Check | C12: =C11-C7
B13: Maximum Debt — Leverage Cap ($) | C13: =Inputs!D73*Debt!C3
B14: Binding Constraint | C14: =IF(C6<=C13,"DSCR Floor","Leverage Cap")
B15: Final Debt Amount ($) | C15: =MIN(C6,C13)
B16: Equity Contribution ($) | C16: =C3-C15-C4
B17: Debt: Total Capitalization (%) | C17: =C15/C3
B20: Year N Production | C20: 1 | D20: 2 | E20: 3 | F20: 4 | G20: 5 | H20: 6 | I20: 7 | J20: 8 | K20: 9 | L20: 10 | M20: 11 | N20: 12 | O20: 13 | P20: 14 | Q20: 15 | R20: 16 | S20: 17 | T20: 18 | U20: 19 | V20: 20 | W20: 21 | X20: 22 | Y20: 23 | Z20: 24 | AA20: 25 | AB20: 26 | AC20: 27 | AD20: 28 | AE20: 29 | AF20: 30
A21: Block 2 — Amortization Schedule
B22: Beginning Balance ($) | C22: =C6 | D22: =C26 | E22: =D26 | F22: =E26 | G22: =F26 | H22: =G26 | I22: =H26 | J22: =I26 | K22: =J26 | ... AF22: =AE26
B23: Interest Payment ($) | C23: =C22*$C$8 | D23: =D22*$C$8 | E23: =E22*$C$8 | F23: =F22*$C$8 | G23: =G22*$C$8 | H23: =H22*$C$8 | I23: =I22*$C$8 | J23: =J22*$C$8 | ... AF23: =AF22*$C$8
B24: Total Debt Service ($) | C24: =IF(C20<=$C$9,$C$10,0) | D24: =IF(D20<=$C$9,$C$10,0) | E24: =IF(E20<=$C$9,$C$10,0) | F24: =IF(F20<=$C$9,$C$10,0) | G24: =IF(G20<=$C$9,$C$10,0) | H24: =IF(H20<=$C$9,$C$10,0) | I24: =IF(I20<=$C$9,$C$10,0) | J24: =IF(J20<=$C$9,$C$10,0) | ... AF24: =IF(AF20<=$C$9,$C$10,0)
B25: Principal Payment ($) | C25: =C24-C23 | D25: =D24-D23 | E25: =E24-E23 | F25: =F24-F23 | G25: =G24-G23 | H25: =H24-H23 | I25: =I24-I23 | J25: =J24-J23 | ... AF25: =AF24-AF23
B26: Ending Balance ($) | C26: =C22-C25 | D26: =D22-D25 | E26: =E22-E25 | F26: =F22-F25 | G26: =G22-G25 | H26: =H22-H25 | I26: =I22-I25 | J26: =J22-J25 | ... AF26: =AF22-AF25
B27: Check: Ending Balance Year 18 | T27: =IF(T26<=0.00001,"PASS","FAIL")
A30: Block 3 — DSCR Calculation
A31: Interim CFADS Calc
B32: Total Revenue ($) | C32: =Revenue!C50 | D32: =Revenue!D50 | E32: =Revenue!E50 | F32: =Revenue!F50 | G32: =Revenue!G50 | H32: =Revenue!H50 | I32: =Revenue!I50 | J32: =Revenue!J50 | ... AF32: =Revenue!AF50
B33: Total Opex ($) | C33: =Costs!C25 | D33: =Costs!D25 | E33: =Costs!E25 | F33: =Costs!F25 | G33: =Costs!G25 | H33: =Costs!H25 | I33: =Costs!I25 | J33: =Costs!J25 | ... AF33: =Costs!AF25
B34: EBITDA ($) | C34: =C32-C33 | D34: =D32-D33 | E34: =E32-E33 | F34: =F32-F33 | G34: =G32-G33 | H34: =H32-H33 | I34: =I32-I33 | J34: =J32-J33 | ... AF34: =AF32-AF33
B35: Interest Expense ($) | C35: =C23 | D35: =D23 | E35: =E23 | F35: =F23 | G35: =G23 | H35: =H23 | I35: =I23 | J35: =J23 | ... AF35: =AF23
B36: Applied Depreciation ($) | C36: =Tax!C62 | D36: =Tax!D62 | E36: =Tax!E62 | F36: =Tax!F62 | G36: =Tax!G62 | H36: =Tax!H62 | I36: =Tax!I62 | J36: =Tax!J62 | ... AF36: =Tax!AF62
B37: Taxable Income ($) | C37: =C34-C35-C36 | D37: =D34-D35-D36 | E37: =E34-E35-E36 | F37: =F34-F35-F36 | G37: =G34-G35-G36 | H37: =H34-H35-H36 | I37: =I34-I35-I36 | J37: =J34-J35-J36 | ... AF37: =AF34-AF35-AF36
B38: Cash Tax ($) | C38: =Tax!C71 | D38: =Tax!D71 | E38: =Tax!E71 | F38: =Tax!F71 | G38: =Tax!G71 | H38: =Tax!H71 | I38: =Tax!I71 | J38: =Tax!J71 | ... AF38: =Tax!AF71
B39: Depreciation Add-Back ($) | C39: =Tax!C62 | D39: =Tax!D62 | E39: =Tax!E62 | F39: =Tax!F62 | G39: =Tax!G62 | H39: =Tax!H62 | I39: =Tax!I62 | J39: =Tax!J62 | ... AF39: =Tax!AF62
B40: CFADS ($) | C40: =C34-C38 | D40: =D34-D38 | E40: =E34-E38 | F40: =F34-F38 | G40: =G34-G38 | H40: =H34-H38 | I40: =I34-I38 | J40: =J34-J38 | ... AF40: =AF34-AF38
A42: DSCR Block
B43: CFADS ($) | C43: =C40 | D43: =D40 | E43: =E40 | F43: =F40 | G43: =G40 | H43: =H40 | I43: =I40 | J43: =J40 | ... AF43: =AF40
B44: Total Debt Service ($) | C44: =C24 | D44: =D24 | E44: =E24 | F44: =F24 | G44: =G24 | H44: =H24 | I44: =I24 | J44: =J24 | ... AF44: =AF24
B45: DSCR (Year N) | C45: =IF(C44=0,"N/A",C43/C44) | D45: =IF(D44=0,"N/A",D43/D44) | E45: =IF(E44=0,"N/A",E43/E44) | F45: =IF(F44=0,"N/A",F43/F44) | G45: =IF(G44=0,"N/A",G43/G44) | H45: =IF(H44=0,"N/A",H43/H44) | I45: =IF(I44=0,"N/A",I43/I44) | J45: =IF(J44=0,"N/A",J43/J44) | ... AF45: =IF(AF44=0,"N/A",AF43/AF44)
B46: Minimum DSCR Covenant | C46: =Inputs!$D$69 | D46: =Inputs!$D$69 | E46: =Inputs!$D$69 | F46: =Inputs!$D$69 | G46: =Inputs!$D$69 | H46: =Inputs!$D$69 | I46: =Inputs!$D$69 | J46: =Inputs!$D$69 | ... AF46: =Inputs!$D$69
B47: DSCR Headroom | C47: =C45-C46 | D47: =D45-D46 | E47: =E45-E46 | F47: =F45-F46 | G47: =G45-G46 | H47: =H45-H46 | I47: =I45-I46 | J47: =J45-J46 | ... T47: =T45-T46 | U47: =IFERROR(U45-U46,"") | V47: =IFERROR(V45-V46,"") | W47: =IFERROR(W45-W46,"") | X47: =IFERROR(X45-X46,"") | Y47: =IFERROR(Y45-Y46,"") | Z47: =IFERROR(Z45-Z46,"") | AA47: =IFERROR(AA45-AA46,"") | AB47: =IFERROR(AB45-AB46,"") | ... AF47: =IFERROR(AF45-AF46,"")
B48: Covenant Breach Flag | C48: =IF(C47<0,"BREACH","OK") | D48: =IF(D47<0,"BREACH","OK") | E48: =IF(E47<0,"BREACH","OK") | F48: =IF(F47<0,"BREACH","OK") | G48: =IF(G47<0,"BREACH","OK") | H48: =IF(H47<0,"BREACH","OK") | I48: =IF(I47<0,"BREACH","OK") | J48: =IF(J47<0,"BREACH","OK") | ... AF48: =IF(AF47<0,"BREACH","OK")
B49: Minimum DSCR (debt period) | C49: =MIN(C45:T45)
B50: Average DSCR (debt period) | C50: =AVERAGE(C45:T45)
B51: P50 DSCR (Year 1) | C51: =C40/C44

Sheet Tax
A1: TAX — ITC/PTC Election · MACRS Depreciation · Tax Liability · Optimal: PTC ($74.9M) | Elected: ITC ($69.9M)
A2: Block 1 — Section 48E ITC Calculation
B3: Total Project Cost ($) | C3: =Costs!C13
B4: Less: Development Costs ($) | C4: =Costs!$C$8
B5: Less: Financing Costs ($) | C5: =Costs!$C$12
B6: Eligible Capex for ITC ($) | C6: =C3-C4-C5
B7: ITC Rate (%) | C7: =Inputs!$D$87
B8: Gross ITC Amount ($) | C8: =C6*C7
B9: ITC Transfer Price (¢/$) | C9: =Inputs!$D$88
B10: ITC Cash Proceeds ($) | C10: =C8*C9
B11: ITC Basis Reduction ($) | C11: =C8*0.5
B12: ITC Depreciable Basis ($) | C12: =C6-C11
B15: Year N Production | C15: 1 | D15: 2 | E15: 3 | F15: 4 | G15: 5 | H15: 6 | I15: 7 | J15: 8 | K15: 9 | L15: 10 | M15: 11 | N15: 12 | O15: 13 | P15: 14 | Q15: 15 | R15: 16 | S15: 17 | T15: 18 | U15: 19 | V15: 20 | W15: 21 | X15: 22 | Y15: 23 | Z15: 24 | AA15: 25 | AB15: 26 | AC15: 27 | AD15: 28 | AE15: 29 | AF15: 30
A16: Block 2 — Section 45Y PTC Calculation
B17: Net Delivered Solar Production (MWh) | C17: =Energy!B9 | D17: =Energy!C9 | E17: =Energy!D9 | F17: =Energy!E9 | G17: =Energy!F9 | H17: =Energy!G9 | I17: =Energy!H9 | J17: =Energy!I9 | ... AF17: =Energy!AE9
B18: PTC Rate ($/MWh) | C18: =Inputs!$D$82 | D18: =Inputs!$D$82 | E18: =Inputs!$D$82 | F18: =Inputs!$D$82 | G18: =Inputs!$D$82 | H18: =Inputs!$D$82 | I18: =Inputs!$D$82 | J18: =Inputs!$D$82 | ... AF18: =Inputs!$D$82
B19: PTC Inflation Adjustment Factor | C19: =(1+Inputs!$D$84)^(Tax!C15-1) | D19: =(1+Inputs!$D$84)^(Tax!D15-1) | E19: =(1+Inputs!$D$84)^(Tax!E15-1) | F19: =(1+Inputs!$D$84)^(Tax!F15-1) | G19: =(1+Inputs!$D$84)^(Tax!G15-1) | H19: =(1+Inputs!$D$84)^(Tax!H15-1) | I19: =(1+Inputs!$D$84)^(Tax!I15-1) | J19: =(1+Inputs!$D$84)^(Tax!J15-1) | ... AF19: =(1+Inputs!$D$84)^(Tax!AF15-1)
B20: PTC Rate — Inflation Adjusted ($/MWh) | C20: =C18*C19 | D20: =D18*D19 | E20: =E18*E19 | F20: =F18*F19 | G20: =G18*G19 | H20: =H18*H19 | I20: =I18*I19 | J20: =J18*J19 | ... AF20: =AF18*AF19
B21: PTC Credit Period Flag | C21: =IF(C15<=10,"Active","Expired") | D21: =IF(D15<=10,"Active","Expired") | E21: =IF(E15<=10,"Active","Expired") | F21: =IF(F15<=10,"Active","Expired") | G21: =IF(G15<=10,"Active","Expired") | H21: =IF(H15<=10,"Active","Expired") | I21: =IF(I15<=10,"Active","Expired") | J21: =IF(J15<=10,"Active","Expired") | ... AF21: =IF(AF15<=10,"Active","Expired")
B22: Annual PTC Value ($) | C22: =IF(C15<=10,C17*C20,0) | D22: =IF(D15<=10,D17*D20,0) | E22: =IF(E15<=10,E17*E20,0) | F22: =IF(F15<=10,F17*F20,0) | G22: =IF(G15<=10,G17*G20,0) | H22: =IF(H15<=10,H17*H20,0) | I22: =IF(I15<=10,I17*I20,0) | J22: =IF(J15<=10,J17*J20,0) | ... AF22: =IF(AF15<=10,AF17*AF20,0)
B23: PTC Transfer Price (¢/$) | C23: =Inputs!$D$83 | D23: =Inputs!$D$83 | E23: =Inputs!$D$83 | F23: =Inputs!$D$83 | G23: =Inputs!$D$83 | H23: =Inputs!$D$83 | I23: =Inputs!$D$83 | J23: =Inputs!$D$83 | ... AF23: =Inputs!$D$83
B24: Annual PTC Cash Proceeds ($) | C24: =C22*C23 | D24: =D22*D23 | E24: =E22*E23 | F24: =F22*F23 | G24: =G22*G23 | H24: =H22*H23 | I24: =I22*I23 | J24: =J22*J23 | ... AF24: =AF22*AF23
A27: Block 3a — ITC MACRS Depreciation Schedule
B28: ITC Depreciable Basis ($) | C28: =$C$12 | D28: =$C$12 | E28: =$C$12 | F28: =$C$12 | G28: =$C$12 | H28: =$C$12
B29: MACRS % — Year N | C29: =Inputs!$D$92 | D29: =Inputs!D93 | E29: =Inputs!D94 | F29: =Inputs!D95 | G29: =Inputs!D96 | H29: =Inputs!D97
B30: ITC Annual Depreciation ($) | C30: =C28*C29 | D30: =D28*D29 | E30: =E28*E29 | F30: =F28*F29 | G30: =G28*G29 | H30: =H28*H29
B31: ITC Cumulative Depreciation ($) | C31: =C30 | D31: =C31+D30 | E31: =D31+E30 | F31: =E31+F30 | G31: =F31+G30 | H31: =G31+H30
B32: ITC Depreciation Tax Shield ($) | C32: =C30*Inputs!$D$89 | D32: =D30*Inputs!$D$89 | E32: =E30*Inputs!$D$89 | F32: =F30*Inputs!$D$89 | G32: =G30*Inputs!$D$89 | H32: =H30*Inputs!$D$89
B33: Check: Fully Depreciated | C33: =C31-C28 | D33: =D31-D28 | E33: =E31-E28 | F33: =F31-F28 | G33: =G31-G28 | H33: =H31-H28
A36: Block 3b — PTC MACRS Depreciation Schedule
B37: PTC Depreciable Basis ($) | C37: =$C$6 | D37: =$C$6 | E37: =$C$6 | F37: =$C$6 | G37: =$C$6 | H37: =$C$6
B38: MACRS % — Year N | C38: =Inputs!$D$92 | D38: =Inputs!$D$93 | E38: =Inputs!$D$94 | F38: =Inputs!$D$95 | G38: =Inputs!$D$96 | H38: =Inputs!$D$97
B39: PTC Annual Depreciation ($) | C39: =C37*C38 | D39: =D37*D38 | E39: =E37*E38 | F39: =F37*F38 | G39: =G37*G38 | H39: =H37*H38
B40: PTC Cumulative Depreciation ($) | C40: =C39 | D40: =C40+D39 | E40: =D40+E39 | F40: =E40+F39 | G40: =F40+G39 | H40: =G40+H39
B41: PTC Depreciation Tax Shield ($) | C41: =C39*Inputs!$D$89 | D41: =D39*Inputs!$D$89 | E41: =E39*Inputs!$D$89 | F41: =F39*Inputs!$D$89 | G41: =G39*Inputs!$D$89 | H41: =H39*Inputs!$D$89
B42: Check: Fully Depreciated | C42: =C40-C37 | D42: =D40-D37 | E42: =E40-E37 | F42: =F40-F37 | G42: =G40-G37 | H42: =H40-H37
A45: Block 4 — ITC vs. PTC Comparison
B46: Tax Credit Election | C46: ITC | D46: PTC
B47: NPV of Credit Proceeds ($) | C47: =C10 | D47: =NPV(Inputs!$D$101,Tax!C24:AF24)
B48: Depreciable Basis ($) | C48: =C12 | D48: =C6
B49: NPV of Depreciation Tax Shield ($) | C49: =NPV(Inputs!$D$101,Tax!C32:H32) | D49: =NPV(Inputs!$D$101,Tax!C41:H41)
B50: Additional Equity Required at Close | C50: =0 | D50: =C47
B51: Total Economic Value ($) | C51: =C47+C49 | D51: =D47+D49-D50
B53: Value Difference ($) | C53: =C51-D51
B54: Optimal Election | C54: =IF(C51>D51,"ITC", "PTC")
B55: **Total economic value comparison is on a project basis. From an equity investor perspective, PTC requires $45.5M more equity at close - reducing levered returns substantially despite higher total NPV. ITC is preferred for equity IRR optimization.
A57: Block 5 — Annual Tax Liability
B58: Total Revenue ($) | C58: =Revenue!C50 | D58: =Revenue!D50 | E58: =Revenue!E50 | F58: =Revenue!F50 | G58: =Revenue!G50 | H58: =Revenue!H50 | I58: =Revenue!I50 | J58: =Revenue!J50 | ... AF58: =Revenue!AF50
B59: Total Opex ($) | C59: =Costs!C25 | D59: =Costs!D25 | E59: =Costs!E25 | F59: =Costs!F25 | G59: =Costs!G25 | H59: =Costs!H25 | I59: =Costs!I25 | J59: =Costs!J25 | ... AF59: =Costs!AF25
B60: EBITDA ($) | C60: =C58-C59 | D60: =D58-D59 | E60: =E58-E59 | F60: =F58-F59 | G60: =G58-G59 | H60: =H58-H59 | I60: =I58-I59 | J60: =J58-J59 | ... AF60: =AF58-AF59
B61: Interest Expense ($) | C61: =Debt!C23 | D61: =Debt!D23 | E61: =Debt!E23 | F61: =Debt!F23 | G61: =Debt!G23 | H61: =Debt!H23 | I61: =Debt!I23 | J61: =Debt!J23 | ... AF61: =Debt!AF23
B62: Applied Annual Depreciation ($) | C62: =IF(Inputs!$D$79="ITC",Tax!C30,Tax!C39) | D62: =IF(Inputs!$D$79="ITC",Tax!D30,Tax!D39) | E62: =IF(Inputs!$D$79="ITC",Tax!E30,Tax!E39) | F62: =IF(Inputs!$D$79="ITC",Tax!F30,Tax!F39) | G62: =IF(Inputs!$D$79="ITC",Tax!G30,Tax!G39) | H62: =IF(Inputs!$D$79="ITC",Tax!H30,Tax!H39) | I62: =IF(Inputs!$D$79="ITC",Tax!I30,Tax!I39) | J62: =IF(Inputs!$D$79="ITC",Tax!J30,Tax!J39) | ... AF62: =IF(Inputs!$D$79="ITC",Tax!AF30,Tax!AF39)
B63: Taxable Income ($) | C63: =C60-C61-C62 | D63: =D60-D61-D62 | E63: =E60-E61-E62 | F63: =F60-F61-F62 | G63: =G60-G61-G62 | H63: =H60-H61-H62 | I63: =I60-I61-I62 | J63: =J60-J61-J62 | ... AF63: =AF60-AF61-AF62
B64: Net Operating Loss (NOL) Beginning Balance | C64: =0 | D64: =C67 | E64: =D67 | F64: =E67 | G64: =F67 | H64: =G67 | I64: =H67 | J64: =I67 | K64: =J67 | ... AF64: =AE67
B65: NOL Generated | C65: =MAX(-C63,0) | D65: =MAX(-D63,0) | E65: =MAX(-E63,0) | F65: =MAX(-F63,0) | G65: =MAX(-G63,0) | H65: =MAX(-H63,0) | I65: =MAX(-I63,0) | J65: =MAX(-J63,0) | ... AF65: =MAX(-AF63,0)
B66: NOL Utilized | C66: =IF(C63>0,MIN(C64,0.8*C63),0) | D66: =IF(D63>0,MIN(D64,0.8*D63),0) | E66: =IF(E63>0,MIN(E64,0.8*E63),0) | F66: =IF(F63>0,MIN(F64,0.8*F63),0) | G66: =IF(G63>0,MIN(G64,0.8*G63),0) | H66: =IF(H63>0,MIN(H64,0.8*H63),0) | I66: =IF(I63>0,MIN(I64,0.8*I63),0) | J66: =IF(J63>0,MIN(J64,0.8*J63),0) | ... AF66: =IF(AF63>0,MIN(AF64,0.8*AF63),0)
B67: NOL Ending Balance | C67: =C64+C65-C66 | D67: =D64+D65-D66 | E67: =E64+E65-E66 | F67: =F64+F65-F66 | G67: =G64+G65-G66 | H67: =H64+H65-H66 | I67: =I64+I65-I66 | J67: =J64+J65-J66 | ... AF67: =AF64+AF65-AF66
B68: Taxable Income After NOL | C68: =C63-C66 | D68: =D63-D66 | E68: =E63-E66 | F68: =F63-F66 | G68: =G63-G66 | H68: =H63-H66 | I68: =I63-I66 | J68: =J63-J66 | ... AF68: =AF63-AF66
B69: Pre-Credit Tax ($) | C69: =MAX(C68*Inputs!$D$89,0) | D69: =MAX(D68*Inputs!$D$89,0) | E69: =MAX(E68*Inputs!$D$89,0) | F69: =MAX(F68*Inputs!$D$89,0) | G69: =MAX(G68*Inputs!$D$89,0) | H69: =MAX(H68*Inputs!$D$89,0) | I69: =MAX(I68*Inputs!$D$89,0) | J69: =MAX(J68*Inputs!$D$89,0) | ... AF69: =MAX(AF68*Inputs!$D$89,0)
B70: PTC Applied ($) | C70: =IF(Inputs!$D$79="PTC",Tax!C24,0) | D70: =IF(Inputs!$D$79="PTC",Tax!D24,0) | E70: =IF(Inputs!$D$79="PTC",Tax!E24,0) | F70: =IF(Inputs!$D$79="PTC",Tax!F24,0) | G70: =IF(Inputs!$D$79="PTC",Tax!G24,0) | H70: =IF(Inputs!$D$79="PTC",Tax!H24,0) | I70: =IF(Inputs!$D$79="PTC",Tax!I24,0) | J70: =IF(Inputs!$D$79="PTC",Tax!J24,0) | ... AF70: =IF(Inputs!$D$79="PTC",Tax!AF24,0)
B71: Net Tax Liability ($) | C71: =MAX(C69-C70,0) | D71: =MAX(D69-D70,0) | E71: =MAX(E69-E70,0) | F71: =MAX(F69-F70,0) | G71: =MAX(G69-G70,0) | H71: =MAX(H69-H70,0) | I71: =MAX(I69-I70,0) | J71: =MAX(J69-J70,0) | ... AF71: =MAX(AF69-AF70,0)

Sheet Cashflows
A1: CASHFLOWS — Project IRR: 7.75% · Equity IRR: 9.52% · Equity Multiple: 3.33x · Payback: 11 Years
A2: Block 1 — Project Cash Flow (Unlevered)
B3: Total Capex ($) | C3: =Costs!C13*-1
B4: ITC Cash Proceeds ($) | C4: =IF(Inputs!$D$79="ITC",Tax!$C$10,0)
B5: Net Investment at Close ($) | C5: =C3+C4
B6: Year N Production | C6: 0 | D6: 1 | E6: 2 | F6: 3 | G6: 4 | H6: 5 | I6: 6 | J6: 7 | K6: 8 | L6: 9 | M6: 10 | N6: 11 | O6: 12 | P6: 13 | Q6: 14 | R6: 15 | S6: 16 | T6: 17 | U6: 18 | V6: 19 | W6: 20 | X6: 21 | Y6: 22 | Z6: 23 | AA6: 24 | AB6: 25 | AC6: 26 | AD6: 27 | AE6: 28 | AF6: 29 | AG6: 30
B7: Total Revenue ($) | C7: 0 | D7: =Revenue!C50 | E7: =Revenue!D50 | F7: =Revenue!E50 | G7: =Revenue!F50 | H7: =Revenue!G50 | I7: =Revenue!H50 | J7: =Revenue!I50 | K7: =Revenue!J50 | ... AG7: =Revenue!AF50
B8: Total Opex ($) | C8: 0 | D8: =Costs!C25 | E8: =Costs!D25 | F8: =Costs!E25 | G8: =Costs!F25 | H8: =Costs!G25 | I8: =Costs!H25 | J8: =Costs!I25 | K8: =Costs!J25 | ... AG8: =Costs!AF25
B9: EBITDA ($) | C9: =C7-C8 | D9: =D7-D8 | E9: =E7-E8 | F9: =F7-F8 | G9: =G7-G8 | H9: =H7-H8 | I9: =I7-I8 | J9: =J7-J8 | ... AG9: =AG7-AG8
B10: Applied Depreciation ($) | C10: 0 | D10: =Tax!C62 | E10: =Tax!D62 | F10: =Tax!E62 | G10: =Tax!F62 | H10: =Tax!G62 | I10: =Tax!H62 | J10: =Tax!I62 | K10: =Tax!J62 | ... AG10: =Tax!AF62
B11: Taxable Income (Unlevered) ($) | C11: =C9-C10 | D11: =D9-D10 | E11: =E9-E10 | F11: =F9-F10 | G11: =G9-G10 | H11: =H9-H10 | I11: =I9-I10 | J11: =J9-J10 | ... AG11: =AG9-AG10
B12: Unlevered Cash Tax ($) | C12: =MAX(C11*0.21,0) | D12: =MAX(D11*0.21,0) | E12: =MAX(E11*0.21,0) | F12: =MAX(F11*0.21,0) | G12: =MAX(G11*0.21,0) | H12: =MAX(H11*0.21,0) | I12: =MAX(I11*0.21,0) | J12: =MAX(J11*0.21,0) | ... AG12: =MAX(AG11*0.21,0)
B13: Depreciation Add-Back ($) | C13: 0 | D13: =Tax!C62 | E13: =Tax!D62 | F13: =Tax!E62 | G13: =Tax!F62 | H13: =Tax!G62 | I13: =Tax!H62 | J13: =Tax!I62 | K13: =Tax!J62 | ... AG13: =Tax!AF62
B14: CFADS — Unlevered ($) | C14: =C9-C12 | D14: =D9-D12 | E14: =E9-E12 | F14: =F9-F12 | G14: =G9-G12 | H14: =H9-H12 | I14: =I9-I12 | J14: =J9-J12 | ... AG14: =AG9-AG12
B15: Project Cash Flow ($) | C15: =C5 | D15: =D14 | E15: =E14 | F15: =F14 | G15: =G14 | H15: =H14 | I15: =I14 | J15: =J14 | K15: =K14 | ... AG15: =AG14
B16: Project IRR | C16: =IRR(C15:AG15)
B17: Project NPV ($) | C17: =NPV(Inputs!$D$70,Cashflows!D15:AG15)+Cashflows!C15
A20: Block 2 — Equity Cash Flow (Levered)
B21: Year N Production | C21: 0 | D21: 1 | E21: 2 | F21: 3 | G21: 4 | H21: 5 | I21: 6 | J21: 7 | K21: 8 | L21: 9 | M21: 10 | N21: 11 | O21: 12 | P21: 13 | Q21: 14 | R21: 15 | S21: 16 | T21: 17 | U21: 18 | V21: 19 | W21: 20 | X21: 21 | Y21: 22 | Z21: 23 | AA21: 24 | AB21: 25 | AC21: 26 | AD21: 27 | AE21: 28 | AF21: 29 | AG21: 30
B22: Equity Contribution ($) | C22: =Debt!C16*-1 | D22: 0 | E22: 0 | F22: 0 | G22: 0 | H22: 0 | I22: 0 | J22: 0 | K22: 0 | L22: 0 | M22: 0 | N22: 0 | O22: 0 | P22: 0 | Q22: 0 | R22: 0 | S22: 0 | T22: 0 | U22: 0 | V22: 0 | W22: 0 | X22: 0 | Y22: 0 | Z22: 0 | AA22: 0 | AB22: 0 | AC22: 0 | AD22: 0 | AE22: 0 | AF22: 0 | AG22: 0
B23: Total Revenue ($) | C23: 0 | D23: =Revenue!C50 | E23: =Revenue!D50 | F23: =Revenue!E50 | G23: =Revenue!F50 | H23: =Revenue!G50 | I23: =Revenue!H50 | J23: =Revenue!I50 | K23: =Revenue!J50 | ... AG23: =Revenue!AF50
B24: Total Opex ($) | C24: 0 | D24: =Costs!C25 | E24: =Costs!D25 | F24: =Costs!E25 | G24: =Costs!F25 | H24: =Costs!G25 | I24: =Costs!H25 | J24: =Costs!I25 | K24: =Costs!J25 | ... AG24: =Costs!AF25
B25: EBITDA ($) | C25: =C23-C24 | D25: =D23-D24 | E25: =E23-E24 | F25: =F23-F24 | G25: =G23-G24 | H25: =H23-H24 | I25: =I23-I24 | J25: =J23-J24 | ... AG25: =AG23-AG24
B26: Interest Expense ($) | C26: 0 | D26: =Debt!C23 | E26: =Debt!D23 | F26: =Debt!E23 | G26: =Debt!F23 | H26: =Debt!G23 | I26: =Debt!H23 | J26: =Debt!I23 | K26: =Debt!J23 | ... AG26: =Debt!AF23
B27: Applied Depreciation ($) | C27: 0 | D27: =Tax!C62 | E27: =Tax!D62 | F27: =Tax!E62 | G27: =Tax!F62 | H27: =Tax!G62 | I27: =Tax!H62 | J27: =Tax!I62 | K27: =Tax!J62 | ... AG27: =Tax!AF62
B28: Taxable Income (Levered) ($) | C28: =C25-C26-C27 | D28: =D25-D26-D27 | E28: =E25-E26-E27 | F28: =F25-F26-F27 | G28: =G25-G26-G27 | H28: =H25-H26-H27 | I28: =I25-I26-I27 | J28: =J25-J26-J27 | ... AG28: =AG25-AG26-AG27
B29: Levered Cash Tax ($) | C29: 0 | D29: =Tax!C71 | E29: =Tax!D71 | F29: =Tax!E71 | G29: =Tax!F71 | H29: =Tax!G71 | I29: =Tax!H71 | J29: =Tax!I71 | K29: =Tax!J71 | ... AG29: =Tax!AF71
B30: Annual Interest Tax Shield (Year N) | C30: 0 | D30: =D12-D29 | E30: =E12-E29 | F30: =F12-F29 | G30: =G12-G29 | H30: =H12-H29 | I30: =I12-I29 | J30: =J12-J29 | K30: =K12-K29 | ... AG30: =AG12-AG29
B31: Depreciation Add-Back ($) | C31: 0 | D31: =Tax!C62 | E31: =Tax!D62 | F31: =Tax!E62 | G31: =Tax!F62 | H31: =Tax!G62 | I31: =Tax!H62 | J31: =Tax!I62 | K31: =Tax!J62 | ... AG31: =Tax!AF62
B32: CFADS ($) | C32: =C25-C29 | D32: =D25-D29 | E32: =E25-E29 | F32: =F25-F29 | G32: =G25-G29 | H32: =H25-H29 | I32: =I25-I29 | J32: =J25-J29 | ... AG32: =AG25-AG29
B33: Total Debt Service ($) | C33: 0 | D33: =Debt!C24 | E33: =Debt!D24 | F33: =Debt!E24 | G33: =Debt!F24 | H33: =Debt!G24 | I33: =Debt!H24 | J33: =Debt!I24 | K33: =Debt!J24 | ... AG33: =Debt!AF24
B34: Free Cash Flow to Equity ($) | C34: =C32-C33 | D34: =D32-D33 | E34: =E32-E33 | F34: =F32-F33 | G34: =G32-G33 | H34: =H32-H33 | I34: =I32-I33 | J34: =J32-J33 | ... AG34: =AG32-AG33
B35: Equity Cash Flow ($) | C35: =C22 | D35: =D34 | E35: =E34 | F35: =F34 | G35: =G34 | H35: =H34 | I35: =I34 | J35: =J34 | K35: =K34 | ... AG35: =AG34
B36: Cumulative FCF (Year N) | C36: =C35 | D36: =C36+D35 | E36: =D36+E35 | F36: =E36+F35 | G36: =F36+G35 | H36: =G36+H35 | I36: =H36+I35 | J36: =I36+J35 | K36: =J36+K35 | ... AG36: =AF36+AG35
B37: Equity IRR | C37: =IRR(C35:AG35)
B38: Equity NPV ($) | C38: =NPV(Inputs!$D$102,Cashflows!D35:AG35)+Cashflows!C35
A41: Block 3 — Equity Multiple and Payback
B42: Equity Multiple | C42: =(SUM(D35:AG35)/ABS(C35))
B43: Payback Period | C43: {=MATCH(TRUE(), C36:AG36 >= 0,0)-1}
A46: Block 4 — Returns Summary
B47: Project IRR (%) | C47: =C16
B48: Equity IRR (%) | C48: =C37
B49: Project NPV ($) | C49: =C17
B50: Equity NPV at 12% ($) | C50: =C38
B51: Equity Multiple (x) | C51: =C42
B52: Payback Period (years) | C52: =C43
B53: Total Revenue (30 years) ($) | C53: =SUM(C23:AG23)
B54: Total Opex (30 years) ($) | C54: =SUM(C24:AG24)
B55: Total Levered Taxes Paid ($) | C55: =SUM(C29:AG29)
B56: Total Interest Tax Shield | C56: =SUM(C30:AG30)
B57: Total Debt Service ($) | C57: =SUM(C33:AG33)

Sheet LCOE
A1: LCOE — Solar: $90.88/MWh · System: $69.84/MWh (Lazard ✓) · Min Viable PPA: $49.02/MWh (LBNL ✓)
A2: Block 1 — Solar LCOE
B3: NPV Costs | C3: =Costs!C13+NPV(Inputs!$D$70,Costs!$C$25:$AF$25)
B4: NPV Energy | C4: =NPV(Inputs!$D$70,Energy!$B$9:$AE$9)
B5: Solar LCOE | C5: =C3/C4
A8: Block 2 — System LCOE (Solar + Storage)
B9: NPV Costs | C9: =Costs!C13+NPV(Inputs!$D$70,Costs!$C$25:$AF$25)
B10: NPV Energy | C10: =NPV(Inputs!$D$70,Energy!$B$9:$AE$9)+NPV(Inputs!$D$70,Energy!$B$19:$AE$19)
B11: Solar + Storage LCOE | C11: =C9/C10
A14: Block 3 — Minimum Viable PPA Price
A15: Section A — Current Model Output
B16: Current PPA Price — Year 1 ($/MWh) | C16: =Inputs!$D$30
B17: Current Equity IRR (%) | C17: =Cashflows!$C$48
B18: Current Project IRR (%) | C18: =Cashflows!$C$47
B19: Current LCOE — Solar ($/MWh) | C19: =C5
B20: Current LCOE — System ($/MWh) | C20: =C11
B21: Gap to 12% Equity IRR | C21: =IF(Inputs!$D$102-LCOE!C17>0,Inputs!$D$102-LCOE!C17,0)
A23: Section B — Minimum Viable PPA Price | D23: Notes
B24: Target Equity IRR (%) | C24: =Inputs!$D$102
B25: Minimum Viable PPA Price ($/MWh) | C25: 49.023994 | D25: Based on What-If analysis
B26: Premium over Current Assumption ($/MWh) | C26: =C25-C16
B27: Premium over Current Assumption (%) | C27: =C26/C16
A29: Section C — Benchmarking | D29: Source
B30: Lazard LCOE - Utility Solar+Storage Low ($/MWh) | C30: 50 | D30: Lazard v18.0 (2025)
B31: Lazard LCOE - Utility Solar+Storage High ($/MWh) | C31: 131 | D31: Lazard v18.0 (2025)
B32: LBNL PPA Price Range - Low ($/MWh) | C32: 40 | D32: LBNL Utility-Scale Solar 2024
B33: LBNL PPA Price Range - High ($/MWh) | C33: 65 | D33: LBNL Utility-Scale Solar 2024
B34: Your LCOE vs. Lazard Range | C34: =IF(AND(C11>=C30,C11<=C31),"Within range","Outside range")
B35: Min Viable PPA vs. LBNL Market Range | C35: =IF(AND(C25>=C32,C25<=C33),"Achievable", "Above market")

Sheet Sensitivities
A1: SENSITIVITIES — 10 One-Way · 4 Two-Way · 4 Scenarios · Base: Project IRR 7.75% / Equity IRR 12.87%
A2: Section 1 — Base Case Summary
B3: Project IRR (%) | C3: 0.077493201
B4: Equity IRR (%) | C4: 0.12872343
B5: Min DSCR (x) | C5: 1.3
B6: Equity Multiple (x) | C6: 5.0630511
B7: Payback Period (years) | C7: 9
B8: Total Project Cost ($) | C8: 172100000
B9: Debt Amount ($) | C9: 99094750
B10: Equity Contribution ($) | C10: 27467500
B11: LCOE — System ($/MWh) | C11: 69.840049
B12: Min Viable PPA Price ($/MWh) | C12: 49.023994
A15: Section 2 — One-Way Sensitivity Tables
B16: Sensitivity Table 1 — PPA Price
C17: Scenario | D17: PPA Price | E17: Project IRR | F17: Equity IRR | G17: Min DSCR | H17: Equity Multiple | I17: ΔEquity IRR
C18: Bear | D18: 40 | E18: 0.058047496 | F18: 0.068397259 | G18: 1.3 | H18: 2.8846717 | I18: -0.060326167
C19: Low | D19: 45 | E19: 0.067773192 | F19: 0.092157107 | G19: 1.3 | H19: 3.704281 | I19: -0.036566319
C20: Base | D20: 50 | E20: 0.077493201 | F20: 0.12872343 | G20: 1.3 | H20: 5.0630511 | I20: 0
C21: Mid-High | D21: 55 | E21: 0.087193982 | F21: 0.1451036 | G21: 1.3 | H21: 4.7081787 | I21: 0.01638017
C22: High | D22: 60 | E22: 0.096865949 | F22: 0.1959416 | G22: 1.3 | H22: 6.1402461 | I22: 0.067218177
C23: Bull | D23: 65 | E23: 0.10631531 | F23: 0.28255855 | G23: 1.3 | H23: 8.568364 | I23: 0.15383512
B25: Sensitivity Table 2 — Solar Capacity Factor
C26: Scenario | D26: Capacity Factor (%) | E26: Project IRR | F26: Equity IRR | G26: Min DSCR | H26: Equity Multiple | I26: ΔEquity IRR
C27: P90 | D27: 0.24 | E27: 0.065423096 | F27: 0.086757402 | G27: 1.3 | H27: 3.4123744 | I27: -0.041966024
C28: Low | D28: 0.25 | E28: 0.069494524 | F28: 0.09851266 | G28: 1.3 | H28: 3.8535457 | I28: -0.030210766
C29: Base (P50) | D29: 0.27 | E29: 0.077493201 | F29: 0.12872343 | G29: 1.3 | H29: 5.0630511 | I29: 0
C30: High | D30: 0.29 | E30: 0.085324886 | F30: 0.13614495 | G30: 1.3 | H30: 4.5471035 | I30: 0.0074215283
C31: P10 | D31: 0.31 | E31: 0.093014938 | F31: 0.16868482 | G31: 1.3 | H31: 5.5999723 | I31: 0.039961393
B33: Sensitivity Table 3 — Solar EPC Cost
C34: Scenario | D34: Solar EPC ($/Wdc) | E34: Project IRR | F34: Equity IRR | G34: Min DSCR | H34: Equity Multiple | I34: ΔEquity IRR
C35: Bull | D35: 0.7 | E35: 0.087111906 | F35: 0.14248558 | G35: 1.3 | H35: 4.730058 | I35: 0.013762154
C36: Low | D36: 0.75 | E36: 0.08214957 | F36: 0.12513341 | G36: 1.3 | H36: 4.1894085 | I36: -0.0035900115
C37: Base | D37: 0.8 | E37: 0.077493201 | F37: 0.12872343 | G37: 1.3 | H37: 5.0630511 | I37: 0
C38: High | D38: 0.9 | E38: 0.068976974 | F38: 0.097072877 | G38: 1.3 | H38: 3.8169663 | I38: -0.031650549
C39: Bear | D39: 1 | E39: 0.061359077 | F39: 0.076785409 | G39: 1.3 | H39: 3.0782013 | I39: -0.051938017
B41: Sensitivity Table 4 — BESS EPC Cost
C42: Scenario | D42: BESS EPC ($/kWh) | E42: Project IRR | F42: Equity IRR | G42: Min DSCR | H42: Equity Multiple | I42: ΔEquity IRR
C43: Bull | D43: 180 | E43: 0.085421657 | F43: 0.13623045 | G43: 1.3 | H43: 4.5343398 | I43: 0.0075070261
C44: Low | D44: 200 | E44: 0.08214957 | F44: 0.12513341 | G44: 1.3 | H44: 4.1894085 | I44: -0.0035900115
C45: Base | D45: 230 | E45: 0.077493201 | F45: 0.12872343 | G45: 1.3 | H45: 5.0630511 | I45: 0
C46: High | D46: 280 | E46: 0.070329143 | F46: 0.10132106 | G46: 1.3 | H46: 3.9784435 | I46: -0.027402362
C47: Bear | D47: 320 | E47: 0.065066399 | F47: 0.08598458 | G47: 1.3 | H47: 3.4057267 | I47: -0.042738846
B49: Sensitivity Table 5 — Interconnection Cost
C50: Scenario | D50: Interconnection Cost ($M) | E50: Project IRR | F50: Equity IRR | G50: Min DSCR | H50: Equity Multiple | I50: ΔEquity IRR
C51: Minimal | D51: 5 | E51: 0.085024661 | F51: 0.13481567 | G51: 1.3 | H51: 4.4901964 | I51: 0.0060922437
C52: Low | D52: 10 | E52: 0.081164782 | F52: 0.1220264 | G52: 1.3 | H52: 4.0934527 | I52: -0.0066970263
C53: Base | D53: 15 | E53: 0.077493201 | F53: 0.12872343 | G53: 1.3 | H53: 5.0630511 | I53: 0
C54: High | D54: 25 | E54: 0.07065484 | F54: 0.10238082 | G54: 1.3 | H54: 4.0190311 | I54: -0.026342606
C55: Severe | D55: 40 | E55: 0.061473834 | F55: 0.077054155 | G55: 1.3 | H55: 3.0875709 | I55: -0.051669272
B57: Sensitivity Table 6 — Merchant Price (Post-PPA)
C58: Scenario | D58: Merchant Price ($/MWh) | E58: Project IRR | F58: Equity IRR | G58: Min DSCR | H58: Equity Multiple | I58: ΔEquity IRR
C59: Bear | D59: 20 | E59: 0.073840527 | F59: 0.12320995 | G59: 1.3 | H59: 4.2095874 | I59: -0.0055134802
C60: Low | D60: 28 | E60: 0.075842195 | F60: 0.12626059 | G60: 1.3 | H60: 4.6647681 | I60: -0.0024628362
C61: Base | D61: 35 | E61: 0.077493201 | F61: 0.12872343 | G61: 1.3 | H61: 5.0630511 | I61: 0
C62: High | D62: 42 | E62: 0.079061438 | F62: 0.13102313 | G62: 1.3 | H62: 5.4613342 | I62: 0.0022997002
C63: Bull | D63: 50 | E63: 0.080763447 | F63: 0.13347966 | G63: 1.3 | H63: 5.9165148 | I63: 0.0047562377
B65: Sensitivity Table 7 — Debt Interest Rate
C66: Scenario | D66: Interest Rate (%) | E66: Project IRR | F66: Equity IRR | G66: Min DSCR | H66: Equity Multiple | I66: ΔEquity IRR
C67: Bull | D67: 0.055 | E67: 0.077493201 | F67: 0.14329689 | G67: 1.3 | H67: 4.7485934 | I67: 0.014573468
C68: Low | D68: 0.06 | E68: 0.077493201 | F68: 0.1302886 | G68: 1.3 | H68: 4.3452249 | I68: 0.0015651689
C69: Base | D69: 0.07 | E69: 0.077493201 | F69: 0.12872343 | G69: 1.3 | H69: 5.0630511 | I69: 0
C70: High | D70: 0.08 | E70: 0.077493201 | F70: 0.10459538 | G70: 1.3 | H70: 4.1052474 | I70: -0.024128047
C71: Bear | D71: 0.09 | E71: 0.077493201 | F71: 0.089071533 | G71: 1.3 | H71: 3.5190475 | I71: -0.039651894
B73: Sensitivity Table 8 — BESS Cycles Per Day
C74: Scenario | D74: Cycles/Day | E74: Project IRR | F74: Equity IRR | G74: Min DSCR | H74: Equity Multiple | I74: ΔEquity IRR
C75: Bear | D75: 1 | E75: 0.073273126 | F75: 0.11193225 | G75: 1.3 | H75: 4.3893795 | I75: -0.016791173
C76: Low | D76: 1.1 | E76: 0.074686253 | F76: 0.11718979 | G76: 1.3 | H76: 4.598331 | I76: -0.011533637
C77: Base | D77: 1.3 | E77: 0.077493201 | F77: 0.12872343 | G77: 1.3 | H77: 5.0630511 | I77: 0
C78: High | D78: 1.5 | E78: 0.08027592 | F78: 0.11906657 | G78: 1.3 | H78: 4.006588 | I78: -0.0096568582
C79: Bull | D79: 1.7 | E79: 0.083036091 | F79: 0.12745012 | G79: 1.3 | H79: 4.2699492 | I79: -0.0012733054
B81: Sensitivity Table 9 — RA Accreditation
C82: Scenario | D82: Accredited Capacity (MW) | E82: % of Nameplate | F82: Project IRR | G82: Equity IRR | H82: Min DSCR | I82: Equity Multiple | J82: ΔEquity IRR
C83: Severe haircut | D83: 27 | E83: 0.54 | F83: 0.061804601 | G83: 0.078675786 | H83: 1.3 | I83: 2.916422 | J83: -0.05004764
C84: Moderate haircut | D84: 36 | E84: 0.72 | F84: 0.06986201 | G84: 0.10047262 | H84: 1.3 | I84: 3.7782515 | J84: -0.028250802
C85: Base | D85: 45 | E85: 0.9 | F85: 0.077493201 | G85: 0.12872343 | H85: 1.3 | I85: 5.0630511 | J85: 0
C86: Upside | D86: 48 | E86: 0.96 | F86: 0.079957619 | G86: 0.11820588 | H86: 1.3 | I86: 4.0218985 | J86: -0.01051755
B88: Sensitivity Table 10 — Curtailment Rate
C89: Scenario | D89: Curtailment Rate (%) | E89: Project IRR | F89: Equity IRR | G89: Min DSCR | H89: Equity Multiple | I89: ΔEquity IRR
C90: Low | D90: 0.02 | E90: 0.078868173 | F90: 0.11525704 | G90: 1.3 | H90: 3.881794 | I90: -0.013466386
C91: Base | D91: 0.04 | E91: 0.077493201 | F91: 0.12872343 | G91: 1.3 | H91: 5.0630511 | I91: 0
C92: High | D92: 0.07 | E92: 0.075425007 | F92: 0.11951955 | G92: 1.3 | H92: 4.6981257 | I92: -0.0092038788
C93: Severe | D93: 0.12 | E93: 0.071962176 | F93: 0.10623933 | G93: 1.3 | H93: 4.18189 | I93: -0.022484093
A95: Section 3 — Two-Way Sensitivity Tables
B96: Base Case Inputs
B97: PPA Price ($/MWh) | C97: 50
B98: Solar EPC Cost ($/Wdc) | C98: 0.8
B99: Capacity Factor (%) | C99: 0.27
B100: Merchant Price ($/MWh) | C100: 35
B101: BESS EPC Cost ($/kWh) | C101: 230
B102: BESS Cycles Per Day | C102: 1.3
B103: Interest Rate (%) | C103: 0.07
B105: Two-Way Table 1 — Equity IRR: PPA Price × Solar EPC Cost
D106: PPA Price ($)
B107: Equity IRR | C107: 0.12872343 | D107: 40 | E107: 45 | F107: 50 | G107: 55 | H107: 60 | I107: 65
B108: Solar EPC Cost ($/Wdc) | C108: 0.75 | D108: 0.076933035 | E108: 0.10542436 | F108: 0.12513341 | G108: 0.16676818 | H108: 0.23397348 | I108: 0.36224568
C109: 0.8 | D109: 0.068397259 | E109: 0.092157107 | F109: 0.12872343 | G109: 0.1451036 | H109: 0.1959416 | I109: 0.28255855
C110: 0.9 | D110: 0.054825887 | E110: 0.072613317 | F110: 0.097072877 | G110: 0.13474974 | H110: 0.14749907 | I110: 0.19609291
C111: 1.1 | D111: 0.03591213 | E111: 0.047667005 | F111: 0.062196487 | G111: 0.080921258 | H111: 0.1067287 | I111: 0.12020145
B114: Two-Way Table 2 — Equity IRR: Capacity Factor × Merchant Price
D115: Capacity Factor (%)
...

Sheet Outputs
B2: 100 MWac Solar PV + 50 MW / 200 MWh BESS | CAISO SP15
B3: Project Finance Model · Base Case Dashboard · April 2026
B6: 1 — Project Summary
B7: Core project parameters and contractual framework
B8: Parameter | C8: Value | D8: Notes / Source
B9: Technology | C9: Single-axis tracking PV + AC-coupled Li-ion BESS | D9: Developer assumption
B10: Location / Market | C10: CAISO SP15 — Southern California | D10: CAISO interconnection queue
B11: Solar Capacity | C11: 100 MWac / 120 MWdc (DC:AC 1.2x) | D11: Developer assumption
B12: Storage Capacity | C12: 50 MW / 200 MWh (4-hour duration) | D12: Developer assumption
B13: P50 Capacity Factor | C13: 27% (AC basis) | D13: NREL NSRDB — SP15 region
B14: P90 Capacity Factor | C14: 24% (AC basis) | D14: NREL NSRDB — SP15 region
B15: Project Life | C15: 30 years | D15: Developer assumption
B16: COD Assumption | C16: Year 1 of model (no construction period) | D16: Simplification — see Limitations
B17: PPA Term / Price | C17: 20 years / $50/MWh Year 1 (1.0%/yr escalator) | D17: LBNL Utility-Scale Solar 2024
B18: Post-PPA Merchant | C18: $35/MWh flat real (Years 21–30) | D18: Conservative flat assumption
B19: Tax Credit | C19: ITC — Section 48E / 30% / PWA compliant | D19: IRA Section 48E; IRS guidance
B20: ITC Transfer Price | C20: 92.5¢ per dollar | D20: Norton Rose Tax Equity Outlook 2024
B22: 2 — Sources and Uses
B23: Total project cost and financing structure at financial close
B24: USES | C24: Amount ($) | D24: % of Total
B25: Solar EPC Cost | C25: =Costs!C4 | D25: =C25/$C$31
B26: BESS EPC Cost | C26: =Costs!C5 | D26: =C26/$C$31
B27: Interconnection | C27: =Costs!C7 | D27: =C27/$C$31
B28: Development Costs ($) | C28: =Costs!C8 | D28: =C28/$C$31
B29: Owner's Contingency ($) | C29: =Costs!C9 | D29: =C29/$C$31
B30: Financing Costs ($) | C30: =Costs!C12 | D30: =C30/$C$31
B31: Total Project Cost | C31: =SUM(C25:C30) | D31: =SUM(D25:D30)
B32: SOURCES | C32: Amount ($) | D32: % of Total
B33: Senior Debt | C33: =Debt!C15 | D33: =C33/$C$36
B34: ITC Cash Proceeds | C34: =Debt!C4 | D34: =C34/C36
B35: Equity Contribution | C35: =Debt!C16 | D35: =C35/C36
B36: Total Sources | C36: =SUM(C33:C35)
B37: Check: Uses − Sources | C37: =C31-C36 | D37: =IF(C37=0,"✓ Capital stack closes", "X Capital stack does not close")
B39: 3 — Key Returns
B40: Project and equity returns, debt metrics, and LCOE benchmarks
B41: Project Returns (Unlevered)
B42: Metric | C42: Value | D42: Benchmark / Target | E42: Status
B43: Project IRR (%) | C43: =Cashflows!C47 | D43: > 7.0% (debt cost) | E43: =IF(C43>=0.07,"✓ Accretive", "⚠ Below target")
B44: Project NPV at 7% ($) | C44: =Cashflows!C17 | D44: > $0 | E44: =IF(C44>0,"✓ Positive","⚠ Below hurdle")
B45: Total 30-Year Revenue ($) | C45: =Cashflows!C53 | D45: —
B46: Total 30-Year Opex ($) | C46: =Cashflows!C54 | D46: —
B47: Total Unlevered Taxes Paid ($) | C47: =SUM(Cashflows!C12:AG12) | D47: —
B49: Equity Returns (Levered)
B50: Equity IRR (%) | C50: =Cashflows!C48 | D50: Target: 12.0% | E50: =IF(C50>=0.12,"✓ Accretive", "⚠ Below target")
B51: Gap to 12% Target | C51: =IF(Inputs!D102-Outputs!C50>0,Inputs!D102-Outputs!C50,0) | D51: Min viable PPA: $55.42/MWh
B52: Equity NPV at 12% ($) | C52: =Cashflows!C38 | D52: > $0 at target IRR | E52: =IF(C52>0,"✓ Positive","⚠ Below hurdle")
B53: Equity Multiple (x) | C53: =Cashflows!C51 | D53: Target: > 2.0x | E53: =IF(C53>=2,"✓ Above 2.0x","⚠ Below target")
B54: Payback Period (years) | C54: =Cashflows!C52 | D54: Target: < 20 yrs | E54: =IF(C54<=20,"✓ Strong","⚠ Below target")
B55: Total Debt Service ($) | C55: =Cashflows!C57 | D55: —
B56: Total Levered Taxes Paid ($) | C56: =Cashflows!C55 | D56: —
B57: Total Interest Tax Shield ($) | C57: =Cashflows!C56 | D57: —
B59: Debt Metrics
B60: Debt Amount ($) | C60: =Debt!C15 | D60: DSCR-constrained
B61: Leverage (%) | C61: =Debt!C17 | D61: Max 65% (leverage cap) | E61: =IF(C61<0.65,"✓ Within cap","⚠ Above cap")
B62: Binding Constraint | C62: =Debt!C14 | D62: —
B63: Annual Debt Service ($) | C63: =Debt!C10 | D63: —
B64: Debt Tenor / Rate | C64: =_xlfn.CONCAT(Debt!C9," years / ",TEXT(Debt!C8,"0.0%")) | D64: NREL ATB 2024
B65: Minimum DSCR (x) | C65: =Debt!C11 | D65: Covenant: 1.30x | E65: =IF(ROUND(C65,2)>=1.3,"✓ At floor","⚠ Below hurdle")
B66: Average DSCR (x) | C66: =Debt!C50 | D66: —
B67: P90 DSCR Year 1 (x) | C67: =Debt!C51 | D67: Floor: 1.10x | E67: =IF(ROUND(C67,2)>=1.1,"✓ Clear","⚠ Below hurdle")
B69: 4 — Revenue and Cost Breakdown
B70: Year 1 revenue mix and operating cost structure
B71: Year 1 Revenue ($17,720,254 total)
B72: Revenue Stream | C72: Year 1 ($) | D72: % of Total | E72: BESS Revenue Detail
B73: Solar Energy Revenue (PPA) | C73: =Revenue!C11 | D73: =C73/C77 | E73: Contract: $50/MWh × 223,653 MWh
B74: BESS Energy Arbitrage | C74: =Revenue!C29 | D74: =C74/$C$77 | E74: $38.48/MWh net spread × 56,466 MWh
B75: BESS Resource Adequacy | C75: =Revenue!C36 | D75: =C75/$C$77 | E75: 45 MW × $6/kW-month × 12
B76: BESS Ancillary Services | C76: =Revenue!C47 | D76: =C76/$C$77 | E76: 15 MW × $75/kW-year
B77: Total Year 1 Revenue | C77: =SUM(C73:C76) | D77: =SUM(D73:D76)
B79: Year 1 Operating Costs ($4,480,250 total / 25.3% of revenue)
B80: Cost Item | C80: Year 1 ($) | D80: % of Revenue
B81: Solar Fixed O&M | C81: =Costs!C19 | D81: =C81/$C$77
B82: BESS Fixed O&M | C82: =Costs!C20 | D82: =C82/$C$77
B83: Land Lease | C83: =Costs!C21 | D83: =C83/$C$77
B84: Insurance | C84: =Costs!C22 | D84: =C84/$C$77
B85: Asset Management Fee | C85: =Costs!C23 | D85: =C85/$C$77
B86: Transmission / CAISO Fees | C86: =Costs!C24 | D86: =C86/$C$77
B87: Total Year 1 Opex | C87: =Costs!C25 | D87: =C87/C77
B88: Year 1 EBITDA | C88: =Cashflows!D25 | D88: =C88/C77
B90: 5 — LCOE and Commercial Viability
B91: Levelized cost benchmarking and minimum viable PPA price analysis
B92: Metric | C92: Value | D92: Benchmark / Range | E92: Status
B93: Solar LCOE ($/MWh) | C93: =LCOE!C5 | D93: Reference only
B94: System LCOE ($/MWh) | C94: =LCOE!C11 | D94: Lazard v18: $50–$131/MWh | E94: =IF(LCOE!C34="Within range","✓ Within range","⚠ Outside range")
B95: Current PPA Price ($/MWh) | C95: =LCOE!C16 | D95: LBNL market: $40–$65/MWh | E95: =IF(AND(C95>=40,C95<=65),"✓ Within market","⚠ Outside range")
B96: Min Viable PPA Price ($/MWh) | C96: =LCOE!C25 | D96: LBNL market: $40–$65/MWh | E96: =IF(AND(C96>=40,C96<=65),"✓ Achievable","⚠ Outside range")
B97: Gap to 12% Equity IRR Target | C97: =LCOE!C21 | D97: Requires +$5.42/MWh on PPA | E97: =IF(C97>=0.12,"✓ Accretive", "⚠ Below target")
B99: 6 — Key Assumptions Reference
B100: All assumptions sourced — see INPUTS tab for full citation detail
B101: Resource | C101: Value | D101: Source
B102: P50 Capacity Factor | C102: =_xlfn.CONCAT(TEXT(Inputs!D13, "0%")," (AC basis)") | D102: NREL NSRDB / SAM — SP15
B103: P90 Capacity Factor | C103: =_xlfn.CONCAT(TEXT(Inputs!D14, "0%")," (AC basis)") | D103: NREL NSRDB
B104: Solar Degradation | C104: =_xlfn.CONCAT(TEXT(Inputs!D15,"0.0%")," / year") | D104: NREL PV Reliability Roadmap
B105: BESS Degradation | C105: =_xlfn.CONCAT(TEXT(Inputs!D26,"0.0%")," / year") | D105: NREL ATB 2024
B106: BESS Cycles / Day | C106: =Inputs!D24 | D106: Simplified dispatch assumption
B107: Curtailment Rate | C107: =Inputs!D17 | D107: LBNL Utility-Scale Solar 2024
B108: BESS Round-Trip Eff. | C108: =Inputs!D25 | D108: Standard Li-ion assumption
B109: Costs | C109: Value | D109: Source
B110: Solar EPC | C110: =_xlfn.CONCAT(TEXT(Inputs!D51,"$0.00"),"/Wdc") | D110: NREL ATB 2024 (California adj.)
B111: BESS EPC | C111: =_xlfn.CONCAT(TEXT(Inputs!D52,"$0"),"/kWh") | D111: NREL ATB 2024 / 2024 market data
...
